{"model": [{"X_pattern": [57], "Y_pattern": [162, 21, 72, 118, 154, 190, 297, 319, 342, 392, 410, 458], "supp": 279, "conf": 0.7190721649484536}, {"X_pattern": [-1], "Y_pattern": [57, 162], "supp": 300, "conf": 0.01753821870158721}, {"X_pattern": [87], "Y_pattern": [200, 36, 55, 56, 61, 114, 248, 306, 315, 354, 375, 499], "supp": 203, "conf": 0.5486486486486486}, {"X_pattern": [-1], "Y_pattern": [87, 200], "supp": 271, "conf": 0.015842857560433778}, {"X_pattern": [204], "Y_pattern": [234, 2, 30, 135, 153, 170, 246, 371, 422, 423, 448, 467], "supp": 225, "conf": 0.6097560975609756}, {"X_pattern": [-1], "Y_pattern": [204, 234], "supp": 275, "conf": 0.01607670047645494}, {"X_pattern": [458], "Y_pattern": [200], "supp": 43, "conf": 0.14982578397212543}, {"X_pattern": [496], "Y_pattern": [200], "supp": 30, "conf": 0.13157894736842105}, {"X_pattern": [26, 497, 39, 44], "Y_pattern": [122, 221, 228, 292, 326, 333, 447, 460, 478], "supp": 209, "conf": 1.0}, {"X_pattern": [26, 497, 26, 39, 44], "Y_pattern": [122, 221, 228, 292, 326, 333, 447, 460, 478], "supp": 12, "conf": 1.0}, {"X_pattern": [26, 497], "Y_pattern": [39, 44], "supp": 208, "conf": 0.7732342007434945}, {"X_pattern": [-1], "Y_pattern": [26, 497], "supp": 269, "conf": 0.015725936102423198}, {"X_pattern": [3, 272, 12], "Y_pattern": [37, 46, 53, 78, 314, 372, 397, 445, 468, 500], "supp": 177, "conf": 1.0}, {"X_pattern": [3], "Y_pattern": [272, 12, 37, 46, 53, 78, 314, 372, 397, 468], "supp": 208, "conf": 0.5730027548209367}, {"X_pattern": [-1], "Y_pattern": [3, 272], "supp": 264, "conf": 0.015433632457396743}, {"X_pattern": [-1], "Y_pattern": [3, 272, 12], "supp": 177, "conf": 0.015521323550904681}, {"X_pattern": [-1], "Y_pattern": [40, 108], "supp": 267, "conf": 0.015609014644412616}, {"X_pattern": [108], "Y_pattern": [11, 25, 113, 131, 198, 242, 264, 280, 332, 432, 435], "supp": 233, "conf": 0.6619318181818182}, {"X_pattern": [22], "Y_pattern": [203, 50, 110, 119, 133, 201, 202, 308, 341, 360, 370, 387], "supp": 213, "conf": 0.6358208955223881}, {"X_pattern": [-1], "Y_pattern": [22, 203], "supp": 247, "conf": 0.014439800064306802}, {"X_pattern": [166, 442, 19], "Y_pattern": [66, 67, 127, 163, 179, 197, 205, 253, 256, 268], "supp": 182, "conf": 1.0}, {"X_pattern": [166, 442], "Y_pattern": [19], "supp": 178, "conf": 0.7416666666666667}, {"X_pattern": [-1], "Y_pattern": [166, 442], "supp": 240, "conf": 0.014030574961269767}, {"X_pattern": [-1], "Y_pattern": [442, 19, 66, 67, 205], "supp": 188, "conf": 0.02747654263248663}, {"X_pattern": [442, 19, 66, 67], "Y_pattern": [127, 163, 179, 197, 253, 256, 268], "supp": 195, "conf": 1.0}, {"X_pattern": [166], "Y_pattern": [442, 19, 66, 67, 205], "supp": 203, "conf": 0.6077844311377245}, {"X_pattern": [94, 144, 62], "Y_pattern": [68, 90, 149, 189, 278, 296, 464, 470, 490], "supp": 189, "conf": 1.0}, {"X_pattern": [94, 144, 62], "Y_pattern": [68, 90, 149, 189, 278, 296, 464, 470, 490, 491], "supp": 189, "conf": 1.0}, {"X_pattern": [94, 144, 3, 62], "Y_pattern": [68, 90, 149, 189, 278, 296, 464, 470, 490, 491], "supp": 7, "conf": 1.0}, {"X_pattern": [458, 94, 144, 62], "Y_pattern": [68, 90, 149, 189, 278, 296, 464, 470, 490, 491], "supp": 22, "conf": 1.0}, {"X_pattern": [94], "Y_pattern": [144], "supp": 221, "conf": 0.6758409785932722}, {"X_pattern": [-1], "Y_pattern": [94, 144, 62], "supp": 189, "conf": 0.016573616672999912}, {"X_pattern": [69], "Y_pattern": [125], "supp": 217, "conf": 0.7114754098360656}, {"X_pattern": [69], "Y_pattern": [125, 41, 107, 130, 222, 361, 376, 395, 473, 481, 488, 496], "supp": 222, "conf": 0.7278688524590164}, {"X_pattern": [397], "Y_pattern": [445, 500], "supp": 206, "conf": 0.9716981132075472}, {"X_pattern": [490], "Y_pattern": [491], "supp": 197, "conf": 0.9609756097560975}], "total_encoding_cost": 96992.25992955164, "miner_runtime": 214.23781038125355, "hypercompressed_model": [{"X_pattern": [57], "Y_pattern": [162, 21, 72, 118, 154, 190, 297, 319, 342, 392, 410, 458], "supp": 279, "conf": 0.7190721649484536}, {"X_pattern": [-1], "Y_pattern": [57, 162], "supp": 300, "conf": 0.01753821870158721}, {"X_pattern": [87], "Y_pattern": [200, 36, 55, 56, 61, 114, 248, 306, 315, 354, 375, 499], "supp": 203, "conf": 0.5486486486486486}, {"X_pattern": [-1], "Y_pattern": [87, 200], "supp": 271, "conf": 0.015842857560433778}, {"X_pattern": [204], "Y_pattern": [234, 2, 30, 135, 153, 170, 246, 371, 422, 423, 448, 467], "supp": 225, "conf": 0.6097560975609756}, {"X_pattern": [-1], "Y_pattern": [204, 234], "supp": 275, "conf": 0.01607670047645494}, {"X_pattern": [458], "Y_pattern": [200], "supp": 43, "conf": 0.14982578397212543}, {"X_pattern": [496], "Y_pattern": [200], "supp": 30, "conf": 0.13157894736842105}, {"X_pattern": [26, 497, 39, 44], "Y_pattern": [122, 221, 228, 292, 326, 333, 447, 460, 478], "supp": 209, "conf": 1.0}, {"X_pattern": [26, 497, 26, 39, 44], "Y_pattern": [122, 221, 228, 292, 326, 333, 447, 460, 478], "supp": 12, "conf": 1.0}, {"X_pattern": [26, 497], "Y_pattern": [39, 44], "supp": 208, "conf": 0.7732342007434945}, {"X_pattern": [-1], "Y_pattern": [26, 497], "supp": 269, "conf": 0.015725936102423198}, {"X_pattern": [3, 272, 12], "Y_pattern": [37, 46, 53, 78, 314, 372, 397, 445, 468, 500], "supp": 177, "conf": 1.0}, {"X_pattern": [3], "Y_pattern": [272, 12, 37, 46, 53, 78, 314, 372, 397, 468], "supp": 208, "conf": 0.5730027548209367}, {"X_pattern": [-1], "Y_pattern": [3, 272], "supp": 264, "conf": 0.015433632457396743}, {"X_pattern": [-1], "Y_pattern": [3, 272, 12], "supp": 177, "conf": 0.015521323550904681}, {"X_pattern": [-1], "Y_pattern": [40, 108], "supp": 267, "conf": 0.015609014644412616}, {"X_pattern": [108], "Y_pattern": [11, 25, 113, 131, 198, 242, 264, 280, 332, 432, 435], "supp": 233, "conf": 0.6619318181818182}, {"X_pattern": [22], "Y_pattern": [203, 50, 110, 119, 133, 201, 202, 308, 341, 360, 370, 387], "supp": 213, "conf": 0.6358208955223881}, {"X_pattern": [-1], "Y_pattern": [22, 203], "supp": 247, "conf": 0.014439800064306802}, {"X_pattern": [166, 442, 19], "Y_pattern": [66, 67, 127, 163, 179, 197, 205, 253, 256, 268], "supp": 182, "conf": 1.0}, {"X_pattern": [166, 442], "Y_pattern": [19], "supp": 178, "conf": 0.7416666666666667}, {"X_pattern": [-1], "Y_pattern": [166, 442], "supp": 240, "conf": 0.014030574961269767}, {"X_pattern": [-1], "Y_pattern": [442, 19, 66, 67, 205], "supp": 188, "conf": 0.02747654263248663}, {"X_pattern": [442, 19, 66, 67], "Y_pattern": [127, 163, 179, 197, 253, 256, 268], "supp": 195, "conf": 1.0}, {"X_pattern": [166], "Y_pattern": [442, 19, 66, 67, 205], "supp": 203, "conf": 0.6077844311377245}, {"X_pattern": [94, 144, 62], "Y_pattern": [68, 90, 149, 189, 278, 296, 464, 470, 490], "supp": 189, "conf": 1.0}, {"X_pattern": [94, 144, 62], "Y_pattern": [68, 90, 149, 189, 278, 296, 464, 470, 490, 491], "supp": 189, "conf": 1.0}, {"X_pattern": [94, 144, 3, 62], "Y_pattern": [68, 90, 149, 189, 278, 296, 464, 470, 490, 491], "supp": 7, "conf": 1.0}, {"X_pattern": [458, 94, 144, 62], "Y_pattern": [68, 90, 149, 189, 278, 296, 464, 470, 490, 491], "supp": 22, "conf": 1.0}, {"X_pattern": [94], "Y_pattern": [144], "supp": 221, "conf": 0.6758409785932722}, {"X_pattern": [-1], "Y_pattern": [94, 144, 62], "supp": 189, "conf": 0.016573616672999912}, {"X_pattern": [69], "Y_pattern": [125], "supp": 217, "conf": 0.7114754098360656}, {"X_pattern": [69], "Y_pattern": [125, 41, 107, 130, 222, 361, 376, 395, 473, 481, 488, 496], "supp": 222, "conf": 0.7278688524590164}, {"X_pattern": [397], "Y_pattern": [445, 500], "supp": 206, "conf": 0.9716981132075472}, {"X_pattern": [490], "Y_pattern": [491], "supp": 197, "conf": 0.9609756097560975}], "precision": 0.5256346650308004, "recall": 0.9299135610766044, "F1": 0.6716298291143417}