{"model": [{"X_pattern": [-1], "Y_pattern": [5, 66, 88, 149, 192, 388, 440, 457, 473]}, {"X_pattern": [-1], "Y_pattern": [197, 271, 26, 27, 170, 221, 260, 263, 289, 389, 431]}, {"X_pattern": [-1], "Y_pattern": [208, 488, 30, 41, 116, 134, 173, 204, 234, 340, 437]}, {"X_pattern": [-1], "Y_pattern": [89, 93, 39, 43, 111, 141, 196, 216, 235, 307, 469]}, {"X_pattern": [-1], "Y_pattern": [57, 199, 5, 66, 88, 149, 192, 388, 440, 457, 473]}, {"X_pattern": [-1], "Y_pattern": [160, 15, 45, 60, 129, 168, 237, 290, 352, 453]}, {"X_pattern": [-1], "Y_pattern": [99, 495, 17, 18, 135, 190, 258, 342, 372, 410, 416]}, {"X_pattern": [-1], "Y_pattern": [303, 326, 34, 54, 107, 110, 125, 230, 279, 331, 394]}, {"X_pattern": [-1], "Y_pattern": [220, 259, 79, 142, 145, 181, 211, 266, 360, 419, 462]}, {"X_pattern": [-1], "Y_pattern": [3, 160, 15, 45, 60, 129, 168, 237, 290, 352, 453]}, {"X_pattern": [-1], "Y_pattern": [401, 466, 4, 20, 23, 40, 194, 231, 330, 361, 383]}, {"X_pattern": [-1], "Y_pattern": [34, 54, 107, 110, 125, 230, 279, 331, 394]}, {"X_pattern": [-1], "Y_pattern": [108, 172, 55, 153, 161, 341, 346, 375, 444, 447, 493]}, {"X_pattern": [-1], "Y_pattern": [17, 18, 135, 190, 258, 342, 372, 410, 416]}, {"X_pattern": [-1], "Y_pattern": [4, 20, 23]}, {"X_pattern": [-1], "Y_pattern": [197, 271]}, {"X_pattern": [-1], "Y_pattern": [401, 466]}, {"X_pattern": [-1], "Y_pattern": [142, 145, 181, 211]}, {"X_pattern": [-1], "Y_pattern": [116, 134, 173, 204, 234, 340, 437]}, {"X_pattern": [-1], "Y_pattern": [89, 93]}, {"X_pattern": [-1], "Y_pattern": [79, 142, 145, 181, 211, 266, 360, 419, 462]}, {"X_pattern": [-1], "Y_pattern": [181, 211, 266, 360, 419, 462]}, {"X_pattern": [-1], "Y_pattern": [108, 172]}, {"X_pattern": [-1], "Y_pattern": [303, 326]}, {"X_pattern": [-1], "Y_pattern": [99, 495]}, {"X_pattern": [-1], "Y_pattern": [30, 41, 116, 134, 173, 204, 234, 340, 437]}, {"X_pattern": [-1], "Y_pattern": [108, 172, 55, 153, 161]}, {"X_pattern": [-1], "Y_pattern": [55, 153, 161, 341, 346, 375, 444, 447, 493]}, {"X_pattern": [-1], "Y_pattern": [30, 41, 116, 134]}, {"X_pattern": [-1], "Y_pattern": [237, 290, 352, 453]}, {"X_pattern": [-1], "Y_pattern": [129, 168, 237, 290, 352, 453]}, {"X_pattern": [-1], "Y_pattern": [149, 192, 388, 440]}, {"X_pattern": [-1], "Y_pattern": [259, 79, 142, 145, 181, 211, 266, 360, 419, 462]}, {"X_pattern": [-1], "Y_pattern": [341, 346, 375, 444]}, {"X_pattern": [-1], "Y_pattern": [330, 361, 383]}, {"X_pattern": [-1], "Y_pattern": [111, 141, 196, 216, 235, 307, 469]}, {"X_pattern": [-1], "Y_pattern": [161, 341, 346, 375, 444, 447, 493]}, {"X_pattern": [-1], "Y_pattern": [199, 5, 66, 88, 149, 192, 388, 440, 457, 473]}, {"X_pattern": [-1], "Y_pattern": [231, 330, 361, 383]}, {"X_pattern": [-1], "Y_pattern": [172, 55, 153, 161, 341, 346, 375, 444, 447, 493]}, {"X_pattern": [-1], "Y_pattern": [271, 26, 27, 170, 221, 260, 263, 289, 389, 431]}, {"X_pattern": [-1], "Y_pattern": [3, 160]}, {"X_pattern": [-1], "Y_pattern": [45, 60, 129, 168]}, {"X_pattern": [-1], "Y_pattern": [495, 17, 18, 135, 190, 258, 342, 372, 410, 416]}, {"X_pattern": [-1], "Y_pattern": [4, 20, 23, 40, 194, 231, 330, 361, 383]}, {"X_pattern": [-1], "Y_pattern": [208, 488]}, {"X_pattern": [-1], "Y_pattern": [26, 27, 170, 221, 260, 263, 289, 389, 431]}, {"X_pattern": [-1], "Y_pattern": [45, 60, 129, 168, 237, 290, 352, 453]}, {"X_pattern": [-1], "Y_pattern": [40, 194]}, {"X_pattern": [-1], "Y_pattern": [173, 204, 234]}, {"X_pattern": [-1], "Y_pattern": [326, 34, 54, 107, 110, 125, 230, 279, 331, 394]}, {"X_pattern": [-1], "Y_pattern": [466, 4, 20, 23, 40, 194, 231, 330, 361, 383]}, {"X_pattern": [-1], "Y_pattern": [57, 199]}, {"X_pattern": [-1], "Y_pattern": [125, 230, 279, 331, 394]}, {"X_pattern": [-1], "Y_pattern": [39, 43, 111, 141, 196, 216, 235, 307, 469]}, {"X_pattern": [-1], "Y_pattern": [447, 493]}, {"X_pattern": [-1], "Y_pattern": [375, 444, 447, 493]}, {"X_pattern": [-1], "Y_pattern": [23, 40, 194, 231, 330, 361, 383]}, {"X_pattern": [-1], "Y_pattern": [196, 216, 235, 307, 469]}, {"X_pattern": [-1], "Y_pattern": [93, 39, 43, 111, 141, 196, 216, 235, 307, 469]}, {"X_pattern": [-1], "Y_pattern": [57, 199, 5, 66, 88]}, {"X_pattern": [-1], "Y_pattern": [266, 360, 419, 462]}, {"X_pattern": [-1], "Y_pattern": [220, 259]}, {"X_pattern": [-1], "Y_pattern": [20, 23, 40, 194, 231, 330, 361, 383]}, {"X_pattern": [-1], "Y_pattern": [340, 437]}, {"X_pattern": [-1], "Y_pattern": [303, 326, 34, 54]}, {"X_pattern": [-1], "Y_pattern": [89, 93, 39, 43, 111, 141]}, {"X_pattern": [-1], "Y_pattern": [107, 110]}, {"X_pattern": [-1], "Y_pattern": [220, 259, 79]}, {"X_pattern": [-1], "Y_pattern": [125, 230]}, {"X_pattern": [-1], "Y_pattern": [153, 161, 341, 346, 375, 444, 447, 493]}, {"X_pattern": [-1], "Y_pattern": [43, 111, 141, 196, 216, 235, 307, 469]}, {"X_pattern": [-1], "Y_pattern": [93, 39, 43, 111, 141, 196]}, {"X_pattern": [-1], "Y_pattern": [235, 307, 469]}, {"X_pattern": [-1], "Y_pattern": [54, 107, 110]}, {"X_pattern": [-1], "Y_pattern": [419, 462]}, {"X_pattern": [-1], "Y_pattern": [279, 331, 394]}, {"X_pattern": [-1], "Y_pattern": [488, 30, 41, 116, 134, 173, 204, 234, 340, 437]}, {"X_pattern": [-1], "Y_pattern": [142, 145, 181, 211, 266, 360, 419, 462]}, {"X_pattern": [-1], "Y_pattern": [3, 160, 15]}], "precision": 0.21750000000000003, "recall": 0.8625, "F1": 0.34739583333333335}