{"model": [{"X_pattern": [-1], "Y_pattern": [257, 338, 346], "supp": 263, "conf": 0.06349589570255915}, {"X_pattern": [-1], "Y_pattern": [6, 104, 464], "supp": 260, "conf": 0.06277160791887977}, {"X_pattern": [-1], "Y_pattern": [109, 164, 303], "supp": 245, "conf": 0.05915016900048286}, {"X_pattern": [-1], "Y_pattern": [110, 363, 445], "supp": 250, "conf": 0.06035731530661516}, {"X_pattern": [-1], "Y_pattern": [292, 402, 268], "supp": 240, "conf": 0.05794302269435055}, {"X_pattern": [-1], "Y_pattern": [302, 350, 351], "supp": 239, "conf": 0.057701593433124095}, {"X_pattern": [-1], "Y_pattern": [341, 394, 383], "supp": 236, "conf": 0.05697730564944471}, {"X_pattern": [-1], "Y_pattern": [5, 270, 51], "supp": 230, "conf": 0.05552873008208595}, {"X_pattern": [-1], "Y_pattern": [290, 373, 24], "supp": 230, "conf": 0.05552873008208595}, {"X_pattern": [-1], "Y_pattern": [118, 448, 203], "supp": 232, "conf": 0.05601158860453887}, {"X_pattern": [-1], "Y_pattern": [6, 104], "supp": 350, "conf": 0.05633349428617415}, {"X_pattern": [-1], "Y_pattern": [257, 338], "supp": 341, "conf": 0.05488491871881539}, {"X_pattern": [-1], "Y_pattern": [292, 402], "supp": 332, "conf": 0.05343634315145662}, {"X_pattern": [-1], "Y_pattern": [109, 164], "supp": 322, "conf": 0.05182681474328022}, {"X_pattern": [-1], "Y_pattern": [290, 373], "supp": 318, "conf": 0.05118300338000966}, {"X_pattern": [-1], "Y_pattern": [118, 448], "supp": 322, "conf": 0.05182681474328022}, {"X_pattern": [-1], "Y_pattern": [110, 363], "supp": 328, "conf": 0.05279253178818606}, {"X_pattern": [-1], "Y_pattern": [302, 350], "supp": 314, "conf": 0.05053919201673909}, {"X_pattern": [-1], "Y_pattern": [341, 394], "supp": 312, "conf": 0.05021728633510381}, {"X_pattern": [-1], "Y_pattern": [5, 270], "supp": 309, "conf": 0.049734427812650896}, {"X_pattern": [-1], "Y_pattern": [338, 346], "supp": 263, "conf": 0.042330597135039436}, {"X_pattern": [-1], "Y_pattern": [104, 464], "supp": 262, "conf": 0.04216964429422179}, {"X_pattern": [-1], "Y_pattern": [350, 351], "supp": 239, "conf": 0.038467728955416065}, {"X_pattern": [-1], "Y_pattern": [394, 383], "supp": 236, "conf": 0.03798487043296314}, {"X_pattern": [-1], "Y_pattern": [164, 303], "supp": 247, "conf": 0.039755351681957186}, {"X_pattern": [-1], "Y_pattern": [402, 268], "supp": 240, "conf": 0.0386286817962337}, {"X_pattern": [-1], "Y_pattern": [363, 445], "supp": 251, "conf": 0.04039916304522775}, {"X_pattern": [-1], "Y_pattern": [448, 203], "supp": 232, "conf": 0.03734105906969258}, {"X_pattern": [-1], "Y_pattern": [270, 51], "supp": 230, "conf": 0.0370191533880573}, {"X_pattern": [-1], "Y_pattern": [373, 24], "supp": 230, "conf": 0.0370191533880573}], "total_encoding_cost": 99376.82884969698, "precision": 0.6000000000000002, "recall": 0.8125, "F1": 0.6902654867256639}