{"model": [{"X_pattern": [-1], "Y_pattern": [106, 383, 59, 334, 433], "supp": 161, "conf": 0.05471351865697003}, {"X_pattern": [-1], "Y_pattern": [350, 474, 64, 173, 439], "supp": 163, "conf": 0.05539318969618705}, {"X_pattern": [-1], "Y_pattern": [33, 135, 129, 275, 467], "supp": 159, "conf": 0.05403384761775301}, {"X_pattern": [-1], "Y_pattern": [244, 391, 235, 261, 462], "supp": 159, "conf": 0.05403384761775301}, {"X_pattern": [-1], "Y_pattern": [267, 378, 38, 239, 403], "supp": 159, "conf": 0.05403384761775301}, {"X_pattern": [-1], "Y_pattern": [175, 212, 117, 372, 472], "supp": 158, "conf": 0.0536940120981445}, {"X_pattern": [-1], "Y_pattern": [331, 385, 89, 209, 221], "supp": 156, "conf": 0.05301434105892748}, {"X_pattern": [-1], "Y_pattern": [126, 499, 80, 151, 302], "supp": 153, "conf": 0.05199483450010195}, {"X_pattern": [-1], "Y_pattern": [87, 322, 69, 398, 428], "supp": 150, "conf": 0.050975327941276426}, {"X_pattern": [-1], "Y_pattern": [157, 225, 14, 437, 445], "supp": 148, "conf": 0.05029565690205941}, {"X_pattern": [-1], "Y_pattern": [383, 59, 334, 433], "supp": 161, "conf": 0.043770814925576024}, {"X_pattern": [-1], "Y_pattern": [391, 235, 261, 462], "supp": 159, "conf": 0.043227078094202405}, {"X_pattern": [-1], "Y_pattern": [474, 64, 173, 439], "supp": 163, "conf": 0.044314551756949636}, {"X_pattern": [-1], "Y_pattern": [135, 129, 275, 467], "supp": 159, "conf": 0.043227078094202405}, {"X_pattern": [-1], "Y_pattern": [212, 117, 372, 472], "supp": 160, "conf": 0.04349894650988921}, {"X_pattern": [-1], "Y_pattern": [378, 38, 239, 403], "supp": 159, "conf": 0.043227078094202405}, {"X_pattern": [-1], "Y_pattern": [385, 89, 209, 221], "supp": 156, "conf": 0.04241147284714198}, {"X_pattern": [-1], "Y_pattern": [499, 80, 151, 302], "supp": 153, "conf": 0.04159586760008156}, {"X_pattern": [-1], "Y_pattern": [322, 69, 398, 428], "supp": 150, "conf": 0.04078026235302114}, {"X_pattern": [-1], "Y_pattern": [225, 14, 437, 445], "supp": 148, "conf": 0.040236525521647526}, {"X_pattern": [-1], "Y_pattern": [38, 239, 403], "supp": 160, "conf": 0.03262420988241691}, {"X_pattern": [-1], "Y_pattern": [117, 372, 472], "supp": 160, "conf": 0.03262420988241691}, {"X_pattern": [-1], "Y_pattern": [64, 173, 439], "supp": 163, "conf": 0.03323591381771223}, {"X_pattern": [-1], "Y_pattern": [129, 275, 467], "supp": 159, "conf": 0.032420308570651805}, {"X_pattern": [-1], "Y_pattern": [59, 334, 433], "supp": 161, "conf": 0.03282811119418202}, {"X_pattern": [-1], "Y_pattern": [80, 151, 302], "supp": 154, "conf": 0.031400802011826275}, {"X_pattern": [-1], "Y_pattern": [69, 398, 428], "supp": 150, "conf": 0.030585196764765857}, {"X_pattern": [-1], "Y_pattern": [14, 437, 445], "supp": 148, "conf": 0.030177394141235644}, {"X_pattern": [-1], "Y_pattern": [126, 499], "supp": 345, "conf": 0.04689730170597431}, {"X_pattern": [-1], "Y_pattern": [244, 391], "supp": 342, "conf": 0.0464894990824441}, {"X_pattern": [-1], "Y_pattern": [33, 135], "supp": 331, "conf": 0.044994222796166654}, {"X_pattern": [-1], "Y_pattern": [350, 474], "supp": 334, "conf": 0.045402025419696866}, {"X_pattern": [-1], "Y_pattern": [331, 385], "supp": 326, "conf": 0.044314551756949636}, {"X_pattern": [-1], "Y_pattern": [157, 225], "supp": 303, "conf": 0.04118806497655135}, {"X_pattern": [-1], "Y_pattern": [87, 322], "supp": 310, "conf": 0.042139604431455174}, {"X_pattern": [-1], "Y_pattern": [267, 378], "supp": 311, "conf": 0.04227553863929858}, {"X_pattern": [-1], "Y_pattern": [175, 212], "supp": 294, "conf": 0.03996465710596071}, {"X_pattern": [-1], "Y_pattern": [106, 383], "supp": 297, "conf": 0.040372459729490925}], "total_encoding_cost": 121214.26996513054, "precision": 0.4440789473684211, "recall": 0.84375, "F1": 0.5818965517241379}