{"model": [{"X_pattern": [-1], "Y_pattern": [243, 268]}, {"X_pattern": [-1], "Y_pattern": [103, 129]}, {"X_pattern": [-1], "Y_pattern": [24, 137]}, {"X_pattern": [-1], "Y_pattern": [73, 95]}, {"X_pattern": [-1], "Y_pattern": [135, 258]}, {"X_pattern": [-1], "Y_pattern": [44, 203]}, {"X_pattern": [-1], "Y_pattern": [27, 108]}, {"X_pattern": [-1], "Y_pattern": [168, 200]}, {"X_pattern": [-1], "Y_pattern": [280, 308]}, {"X_pattern": [-1], "Y_pattern": [152, 418]}, {"X_pattern": [-1], "Y_pattern": [44, 203, 2, 48, 300]}, {"X_pattern": [-1], "Y_pattern": [27, 108, 50, 386, 496]}, {"X_pattern": [-1], "Y_pattern": [280, 308, 59, 394, 429]}, {"X_pattern": [-1], "Y_pattern": [73, 95, 68, 208, 256]}, {"X_pattern": [-1], "Y_pattern": [152, 418, 164, 335, 368]}, {"X_pattern": [-1], "Y_pattern": [168, 200, 53, 337, 443]}, {"X_pattern": [-1], "Y_pattern": [135, 258, 21, 102, 184]}, {"X_pattern": [-1], "Y_pattern": [243, 268, 92, 295, 377]}, {"X_pattern": [-1], "Y_pattern": [24, 137, 174, 278, 412]}, {"X_pattern": [-1], "Y_pattern": [418, 164, 335, 368]}, {"X_pattern": [-1], "Y_pattern": [95, 68, 208, 256]}, {"X_pattern": [-1], "Y_pattern": [103, 129, 112, 124, 493]}, {"X_pattern": [-1], "Y_pattern": [203, 2, 48, 300]}, {"X_pattern": [-1], "Y_pattern": [258, 21, 102, 184]}, {"X_pattern": [-1], "Y_pattern": [108, 50, 386, 496]}, {"X_pattern": [-1], "Y_pattern": [112, 124, 493]}, {"X_pattern": [-1], "Y_pattern": [53, 337, 443]}, {"X_pattern": [-1], "Y_pattern": [174, 278, 412]}, {"X_pattern": [-1], "Y_pattern": [92, 295, 377]}, {"X_pattern": [-1], "Y_pattern": [308, 59, 394, 429]}, {"X_pattern": [-1], "Y_pattern": [268, 92, 295, 377]}, {"X_pattern": [-1], "Y_pattern": [59, 394, 429]}], "precision": 0.52734375, "recall": 0.84375, "F1": 0.6490384615384616}