{"model": [{"X_pattern": [-1], "Y_pattern": [57, 162], "supp": 366, "conf": 0.04963048342260492}, {"X_pattern": [-1], "Y_pattern": [150, 469], "supp": 331, "conf": 0.044884398942301174}, {"X_pattern": [-1], "Y_pattern": [130, 471], "supp": 334, "conf": 0.045291206183470066}, {"X_pattern": [-1], "Y_pattern": [155, 459], "supp": 279, "conf": 0.03783307342870703}, {"X_pattern": [-1], "Y_pattern": [57, 162, 72, 118, 342], "supp": 179, "conf": 0.06068208014102651}, {"X_pattern": [-1], "Y_pattern": [144, 296], "supp": 329, "conf": 0.044613194114855245}, {"X_pattern": [-1], "Y_pattern": [126, 370, 69, 221, 361], "supp": 156, "conf": 0.05288494135195606}, {"X_pattern": [-1], "Y_pattern": [21, 392, 191, 297, 411], "supp": 172, "conf": 0.05830903790087463}, {"X_pattern": [-1], "Y_pattern": [481, 489, 40, 106, 496], "supp": 162, "conf": 0.05491897755780053}, {"X_pattern": [130, 471], "Y_pattern": [94, 374, 393], "supp": 161, "conf": 0.4820359281437126}, {"X_pattern": [-1], "Y_pattern": [46, 445], "supp": 297, "conf": 0.040273916875720385}, {"X_pattern": [-1], "Y_pattern": [481, 489], "supp": 327, "conf": 0.04434198928740932}, {"X_pattern": [46, 445], "Y_pattern": [37, 314, 468], "supp": 145, "conf": 0.4882154882154882}, {"X_pattern": [150, 469], "Y_pattern": [61, 278, 463], "supp": 144, "conf": 0.4350453172205438}, {"X_pattern": [144, 296], "Y_pattern": [68, 89, 491], "supp": 162, "conf": 0.49240121580547114}, {"X_pattern": [-1], "Y_pattern": [12, 80], "supp": 301, "conf": 0.04081632653061224}, {"X_pattern": [-1], "Y_pattern": [126, 370], "supp": 296, "conf": 0.04013831446199742}, {"X_pattern": [-1], "Y_pattern": [12, 80, 55, 397, 500], "supp": 158, "conf": 0.05356295342057088}, {"X_pattern": [-1], "Y_pattern": [21, 392], "supp": 326, "conf": 0.04420638687368635}, {"X_pattern": [155, 459], "Y_pattern": [3, 273, 319], "supp": 132, "conf": 0.4731182795698925}, {"X_pattern": [459], "Y_pattern": [3, 273, 319], "supp": 135, "conf": 0.4426229508196721}], "total_encoding_cost": 68310.61880136526, "precision": 0.8862433862433863, "recall": 0.921875, "F1": 0.9037081066252115}