{"model": [{"X_pattern": [-1], "Y_pattern": [66, 60, 157, 444], "supp": 97, "conf": 0.022495361781076067}, {"X_pattern": [-1], "Y_pattern": [117, 256, 118, 380, 399], "supp": 104, "conf": 0.030148423005565864}, {"X_pattern": [-1], "Y_pattern": [59, 273, 88, 362, 448], "supp": 105, "conf": 0.030438311688311688}, {"X_pattern": [-1], "Y_pattern": [381, 193, 437, 464], "supp": 85, "conf": 0.01971243042671614}, {"X_pattern": [-1], "Y_pattern": [140, 239, 85, 109, 131], "supp": 114, "conf": 0.03304730983302412}, {"X_pattern": [-1], "Y_pattern": [449, 479, 9, 46, 186], "supp": 110, "conf": 0.03188775510204082}, {"X_pattern": [-1], "Y_pattern": [284, 310, 56, 245, 417], "supp": 103, "conf": 0.029858534322820037}, {"X_pattern": [-1], "Y_pattern": [323, 162, 221, 316], "supp": 86, "conf": 0.019944341372912802}, {"X_pattern": [-1], "Y_pattern": [398, 388, 394, 411], "supp": 92, "conf": 0.021335807050092765}, {"X_pattern": [-1], "Y_pattern": [18, 120, 159, 274, 356], "supp": 90, "conf": 0.026089981447124305}, {"X_pattern": [-1], "Y_pattern": [341, 420, 148, 163, 353], "supp": 93, "conf": 0.026959647495361783}, {"X_pattern": [-1], "Y_pattern": [376, 495, 91, 342, 469], "supp": 113, "conf": 0.03275742115027829}, {"X_pattern": [-1], "Y_pattern": [212, 229, 116, 299, 384], "supp": 111, "conf": 0.032177643784786644}, {"X_pattern": [-1], "Y_pattern": [258, 492, 29, 72, 445], "supp": 101, "conf": 0.029278756957328386}, {"X_pattern": [-1], "Y_pattern": [340, 461, 106, 232, 413], "supp": 89, "conf": 0.02580009276437848}, {"X_pattern": [-1], "Y_pattern": [10, 323, 162, 221, 316], "supp": 86, "conf": 0.024930426716141003}, {"X_pattern": [-1], "Y_pattern": [328, 398, 388, 394, 411], "supp": 92, "conf": 0.026669758812615955}, {"X_pattern": [-1], "Y_pattern": [44, 304, 14, 235, 424], "supp": 91, "conf": 0.02637987012987013}, {"X_pattern": [-1], "Y_pattern": [395, 412, 58, 291, 488], "supp": 80, "conf": 0.02319109461966605}, {"X_pattern": [-1], "Y_pattern": [205, 404, 344, 349, 421], "supp": 102, "conf": 0.029568645640074213}, {"X_pattern": [-1], "Y_pattern": [309, 493, 82, 210, 475], "supp": 103, "conf": 0.029858534322820037}, {"X_pattern": [-1], "Y_pattern": [234, 476, 32, 266, 467], "supp": 90, "conf": 0.026089981447124305}, {"X_pattern": [19], "Y_pattern": [66, 60, 157, 444], "supp": 97, "conf": 0.6339869281045751}, {"X_pattern": [-1], "Y_pattern": [209, 211, 57, 151, 197], "supp": 92, "conf": 0.026669758812615955}, {"X_pattern": [-1], "Y_pattern": [37, 301, 45, 292, 416], "supp": 101, "conf": 0.029278756957328386}, {"X_pattern": [-1], "Y_pattern": [247, 297, 305, 423, 465], "supp": 81, "conf": 0.023480983302411874}, {"X_pattern": [-1], "Y_pattern": [55, 223, 7, 346, 351], "supp": 89, "conf": 0.02580009276437848}, {"X_pattern": [-1], "Y_pattern": [358, 489, 90, 95, 372], "supp": 83, "conf": 0.024060760667903525}, {"X_pattern": [326], "Y_pattern": [381, 193, 437, 464], "supp": 85, "conf": 0.5902777777777778}, {"X_pattern": [-1], "Y_pattern": [309, 493], "supp": 130, "conf": 0.015074211502782932}, {"X_pattern": [-1], "Y_pattern": [59, 273], "supp": 145, "conf": 0.016813543599257887}, {"X_pattern": [-1], "Y_pattern": [376, 495], "supp": 145, "conf": 0.016813543599257887}, {"X_pattern": [-1], "Y_pattern": [10, 323], "supp": 119, "conf": 0.013798701298701298}, {"X_pattern": [-1], "Y_pattern": [247, 297], "supp": 107, "conf": 0.012407235621521335}, {"X_pattern": [-1], "Y_pattern": [326, 381], "supp": 128, "conf": 0.014842300556586271}, {"X_pattern": [-1], "Y_pattern": [449, 479], "supp": 143, "conf": 0.016581632653061226}, {"X_pattern": [-1], "Y_pattern": [209, 211], "supp": 129, "conf": 0.014958256029684602}, {"X_pattern": [-1], "Y_pattern": [37, 301], "supp": 121, "conf": 0.01403061224489796}, {"X_pattern": [-1], "Y_pattern": [395, 412], "supp": 108, "conf": 0.012523191094619666}, {"X_pattern": [-1], "Y_pattern": [234, 476], "supp": 116, "conf": 0.013450834879406308}, {"X_pattern": [-1], "Y_pattern": [340, 461], "supp": 118, "conf": 0.01368274582560297}, {"X_pattern": [-1], "Y_pattern": [19, 66], "supp": 130, "conf": 0.015074211502782932}, {"X_pattern": [-1], "Y_pattern": [284, 310], "supp": 136, "conf": 0.015769944341372914}, {"X_pattern": [-1], "Y_pattern": [140, 239], "supp": 140, "conf": 0.016233766233766232}, {"X_pattern": [-1], "Y_pattern": [358, 489], "supp": 114, "conf": 0.013218923933209647}, {"X_pattern": [-1], "Y_pattern": [44, 304], "supp": 116, "conf": 0.013450834879406308}, {"X_pattern": [-1], "Y_pattern": [18, 120], "supp": 120, "conf": 0.013914656771799629}, {"X_pattern": [-1], "Y_pattern": [117, 256], "supp": 137, "conf": 0.015885899814471242}, {"X_pattern": [-1], "Y_pattern": [205, 404], "supp": 130, "conf": 0.015074211502782932}, {"X_pattern": [-1], "Y_pattern": [341, 420], "supp": 123, "conf": 0.01426252319109462}, {"X_pattern": [-1], "Y_pattern": [212, 229], "supp": 135, "conf": 0.01565398886827458}, {"X_pattern": [-1], "Y_pattern": [258, 492], "supp": 135, "conf": 0.01565398886827458}, {"X_pattern": [239], "Y_pattern": [85, 109, 131], "supp": 117, "conf": 0.7452229299363057}, {"X_pattern": [-1], "Y_pattern": [328, 398], "supp": 121, "conf": 0.01403061224489796}, {"X_pattern": [-1], "Y_pattern": [55, 223], "supp": 125, "conf": 0.01449443413729128}], "total_encoding_cost": 78873.98287139882, "precision": 0.7772366522366523, "recall": 0.8549603174603174, "F1": 0.8142479213907785}