{"model": [{"X_pattern": [-1], "Y_pattern": [244, 391, 235, 261, 462], "supp": 262, "conf": 0.07589803012746234}, {"X_pattern": [-1], "Y_pattern": [126, 499, 80, 151, 302], "supp": 256, "conf": 0.07415990730011587}, {"X_pattern": [-1], "Y_pattern": [33, 135, 129, 275, 467], "supp": 251, "conf": 0.07271147161066048}, {"X_pattern": [-1], "Y_pattern": [267, 378, 38, 239, 403], "supp": 239, "conf": 0.06923522595596755}, {"X_pattern": [-1], "Y_pattern": [157, 225, 14, 437, 445], "supp": 238, "conf": 0.06894553881807648}, {"X_pattern": [-1], "Y_pattern": [350, 474, 64, 173, 439], "supp": 247, "conf": 0.07155272305909617}, {"X_pattern": [-1], "Y_pattern": [87, 322, 69, 398, 428], "supp": 236, "conf": 0.06836616454229433}, {"X_pattern": [-1], "Y_pattern": [175, 212, 117, 372, 472], "supp": 228, "conf": 0.0660486674391657}, {"X_pattern": [-1], "Y_pattern": [331, 385, 89, 209, 221], "supp": 228, "conf": 0.0660486674391657}, {"X_pattern": [-1], "Y_pattern": [106, 383, 59, 334, 433], "supp": 218, "conf": 0.06315179606025492}, {"X_pattern": [-1], "Y_pattern": [391, 235, 261, 462], "supp": 262, "conf": 0.06071842410196987}, {"X_pattern": [-1], "Y_pattern": [499, 80, 151, 302], "supp": 256, "conf": 0.0593279258400927}, {"X_pattern": [-1], "Y_pattern": [135, 129, 275, 467], "supp": 252, "conf": 0.05840092699884125}, {"X_pattern": [-1], "Y_pattern": [378, 38, 239, 403], "supp": 240, "conf": 0.055619930475086905}, {"X_pattern": [-1], "Y_pattern": [474, 64, 173, 439], "supp": 248, "conf": 0.0574739281575898}, {"X_pattern": [-1], "Y_pattern": [225, 14, 437, 445], "supp": 241, "conf": 0.055851680185399766}, {"X_pattern": [-1], "Y_pattern": [322, 69, 398, 428], "supp": 236, "conf": 0.054692931633835457}, {"X_pattern": [-1], "Y_pattern": [385, 89, 209, 221], "supp": 228, "conf": 0.05283893395133256}, {"X_pattern": [-1], "Y_pattern": [212, 117, 372, 472], "supp": 230, "conf": 0.05330243337195829}, {"X_pattern": [-1], "Y_pattern": [383, 59, 334, 433], "supp": 218, "conf": 0.05052143684820394}, {"X_pattern": [-1], "Y_pattern": [80, 151, 302], "supp": 257, "conf": 0.04466975666280417}, {"X_pattern": [-1], "Y_pattern": [129, 275, 467], "supp": 254, "conf": 0.04414831981460023}, {"X_pattern": [-1], "Y_pattern": [64, 173, 439], "supp": 250, "conf": 0.043453070683661645}, {"X_pattern": [-1], "Y_pattern": [38, 239, 403], "supp": 240, "conf": 0.04171494785631518}, {"X_pattern": [-1], "Y_pattern": [14, 437, 445], "supp": 241, "conf": 0.04188876013904983}, {"X_pattern": [-1], "Y_pattern": [69, 398, 428], "supp": 236, "conf": 0.04101969872537659}, {"X_pattern": [-1], "Y_pattern": [117, 372, 472], "supp": 231, "conf": 0.04015063731170336}, {"X_pattern": [-1], "Y_pattern": [89, 209, 221], "supp": 228, "conf": 0.03962920046349942}, {"X_pattern": [-1], "Y_pattern": [59, 334, 433], "supp": 218, "conf": 0.03789107763615296}, {"X_pattern": [-1], "Y_pattern": [126, 499], "supp": 338, "conf": 0.039165701042873695}, {"X_pattern": [-1], "Y_pattern": [129, 275], "supp": 254, "conf": 0.029432213209733486}, {"X_pattern": [-1], "Y_pattern": [33, 135], "supp": 327, "conf": 0.03789107763615295}, {"X_pattern": [-1], "Y_pattern": [350, 474], "supp": 329, "conf": 0.03812282734646582}, {"X_pattern": [-1], "Y_pattern": [244, 391], "supp": 335, "conf": 0.0388180764774044}, {"X_pattern": [-1], "Y_pattern": [173, 439], "supp": 250, "conf": 0.028968713789107765}, {"X_pattern": [-1], "Y_pattern": [331, 385], "supp": 317, "conf": 0.03673232908458864}, {"X_pattern": [-1], "Y_pattern": [437, 445], "supp": 241, "conf": 0.027925840092699883}, {"X_pattern": [-1], "Y_pattern": [398, 428], "supp": 236, "conf": 0.027346465816917728}, {"X_pattern": [-1], "Y_pattern": [267, 378], "supp": 311, "conf": 0.03603707995365006}, {"X_pattern": [-1], "Y_pattern": [372, 472], "supp": 231, "conf": 0.026767091541135574}, {"X_pattern": [-1], "Y_pattern": [175, 212], "supp": 294, "conf": 0.03406720741599073}, {"X_pattern": [-1], "Y_pattern": [157, 225], "supp": 297, "conf": 0.034414831981460024}, {"X_pattern": [-1], "Y_pattern": [87, 322], "supp": 306, "conf": 0.0354577056778679}, {"X_pattern": [-1], "Y_pattern": [106, 383], "supp": 291, "conf": 0.033719582850521436}], "total_encoding_cost": 140863.62293540096, "precision": 0.3835227272727273, "recall": 0.84375, "F1": 0.52734375}