{"model": [{"X_pattern": [-1], "Y_pattern": [293, 433, 17, 384, 391], "supp": 138, "conf": 0.040095298971468414}, {"X_pattern": [-1], "Y_pattern": [313, 362, 65, 141, 358], "supp": 140, "conf": 0.04067639026090999}, {"X_pattern": [-1], "Y_pattern": [74, 401, 259, 469, 496], "supp": 135, "conf": 0.03922366203730606}, {"X_pattern": [-1], "Y_pattern": [297, 340, 16, 146, 492], "supp": 132, "conf": 0.0383520251031437}, {"X_pattern": [-1], "Y_pattern": [237, 473, 59, 217, 308], "supp": 131, "conf": 0.03806147945842291}, {"X_pattern": [-1], "Y_pattern": [281, 387, 148, 314, 316], "supp": 123, "conf": 0.03573711430065663}, {"X_pattern": [-1], "Y_pattern": [63, 147, 28, 291, 321], "supp": 118, "conf": 0.034284386077052705}, {"X_pattern": [-1], "Y_pattern": [35, 150, 175, 251, 409], "supp": 120, "conf": 0.03486547736649427}, {"X_pattern": [-1], "Y_pattern": [8, 41, 261, 394, 459], "supp": 120, "conf": 0.03486547736649427}, {"X_pattern": [-1], "Y_pattern": [247, 471, 182, 374, 500], "supp": 120, "conf": 0.03486547736649427}, {"X_pattern": [-1], "Y_pattern": [129, 227, 4, 248, 364], "supp": 117, "conf": 0.03399384043233192}, {"X_pattern": [-1], "Y_pattern": [309, 470, 78, 236, 312], "supp": 115, "conf": 0.033412749142890344}, {"X_pattern": [-1], "Y_pattern": [36, 134, 5, 19, 499], "supp": 119, "conf": 0.03457493172177349}, {"X_pattern": [-1], "Y_pattern": [15, 256, 300, 324, 437], "supp": 119, "conf": 0.03457493172177349}, {"X_pattern": [-1], "Y_pattern": [346, 443, 98, 105, 322], "supp": 116, "conf": 0.03370329478761113}, {"X_pattern": [-1], "Y_pattern": [70, 106, 75, 85, 490], "supp": 111, "conf": 0.0322505665640072}, {"X_pattern": [-1], "Y_pattern": [433, 17, 384, 391], "supp": 138, "conf": 0.03207623917717473}, {"X_pattern": [-1], "Y_pattern": [362, 65, 141, 358], "supp": 141, "conf": 0.03277354872450462}, {"X_pattern": [-1], "Y_pattern": [10, 154, 171, 424, 435], "supp": 112, "conf": 0.03254111220872799}, {"X_pattern": [-1], "Y_pattern": [104, 169, 403, 420, 497], "supp": 105, "conf": 0.03050729269568249}, {"X_pattern": [-1], "Y_pattern": [401, 259, 469, 496], "supp": 135, "conf": 0.03137892962984485}, {"X_pattern": [-1], "Y_pattern": [340, 16, 146, 492], "supp": 132, "conf": 0.030681620082514963}, {"X_pattern": [-1], "Y_pattern": [95, 244, 11, 37, 177], "supp": 106, "conf": 0.030797838340403276}, {"X_pattern": [-1], "Y_pattern": [473, 59, 217, 308], "supp": 131, "conf": 0.030449183566738335}, {"X_pattern": [-1], "Y_pattern": [387, 148, 314, 316], "supp": 123, "conf": 0.028589691440525308}, {"X_pattern": [-1], "Y_pattern": [150, 175, 251, 409], "supp": 120, "conf": 0.02789238189319542}, {"X_pattern": [-1], "Y_pattern": [41, 261, 394, 459], "supp": 120, "conf": 0.02789238189319542}, {"X_pattern": [-1], "Y_pattern": [103, 477, 22, 53, 379], "supp": 95, "conf": 0.027601836248474634}, {"X_pattern": [-1], "Y_pattern": [227, 4, 248, 364], "supp": 119, "conf": 0.027659945377418792}, {"X_pattern": [-1], "Y_pattern": [471, 182, 374, 500], "supp": 120, "conf": 0.02789238189319542}, {"X_pattern": [-1], "Y_pattern": [147, 28, 291, 321], "supp": 118, "conf": 0.027427508861642164}, {"X_pattern": [-1], "Y_pattern": [134, 5, 19, 499], "supp": 122, "conf": 0.02835725492474868}, {"X_pattern": [-1], "Y_pattern": [470, 78, 236, 312], "supp": 115, "conf": 0.026730199314312277}, {"X_pattern": [-1], "Y_pattern": [443, 98, 105, 322], "supp": 116, "conf": 0.026962635830088906}, {"X_pattern": [-1], "Y_pattern": [256, 300, 324, 437], "supp": 119, "conf": 0.027659945377418792}, {"X_pattern": [-1], "Y_pattern": [106, 75, 85, 490], "supp": 111, "conf": 0.025800453251205765}, {"X_pattern": [-1], "Y_pattern": [154, 171, 424, 435], "supp": 111, "conf": 0.025800453251205765}, {"X_pattern": [-1], "Y_pattern": [244, 11, 37, 177], "supp": 107, "conf": 0.02487070718809925}, {"X_pattern": [-1], "Y_pattern": [169, 403, 420, 497], "supp": 105, "conf": 0.024405834156545993}, {"X_pattern": [-1], "Y_pattern": [65, 141, 358], "supp": 141, "conf": 0.024580161543378467}, {"X_pattern": [-1], "Y_pattern": [477, 22, 53, 379], "supp": 96, "conf": 0.022313905514556337}, {"X_pattern": [-1], "Y_pattern": [259, 469, 496], "supp": 134, "conf": 0.023359869835551165}, {"X_pattern": [-1], "Y_pattern": [59, 217, 308], "supp": 131, "conf": 0.022836887675053753}, {"X_pattern": [-1], "Y_pattern": [148, 314, 316], "supp": 123, "conf": 0.02144226858039398}, {"X_pattern": [-1], "Y_pattern": [182, 374, 500], "supp": 120, "conf": 0.020919286419896568}, {"X_pattern": [-1], "Y_pattern": [175, 251, 409], "supp": 120, "conf": 0.020919286419896568}, {"X_pattern": [-1], "Y_pattern": [261, 394, 459], "supp": 120, "conf": 0.020919286419896568}, {"X_pattern": [-1], "Y_pattern": [78, 236, 312], "supp": 116, "conf": 0.02022197687256668}, {"X_pattern": [-1], "Y_pattern": [5, 19, 499], "supp": 122, "conf": 0.02126794119356151}, {"X_pattern": [-1], "Y_pattern": [28, 291, 321], "supp": 118, "conf": 0.020570631646231623}, {"X_pattern": [-1], "Y_pattern": [98, 105, 322], "supp": 116, "conf": 0.02022197687256668}, {"X_pattern": [-1], "Y_pattern": [171, 424, 435], "supp": 112, "conf": 0.019524667325236795}, {"X_pattern": [-1], "Y_pattern": [75, 85, 490], "supp": 111, "conf": 0.019350339938404324}, {"X_pattern": [-1], "Y_pattern": [11, 37, 177], "supp": 107, "conf": 0.018653030391074438}, {"X_pattern": [-1], "Y_pattern": [74, 401], "supp": 180, "conf": 0.020919286419896564}, {"X_pattern": [-1], "Y_pattern": [293, 433], "supp": 173, "conf": 0.020105758614678365}, {"X_pattern": [-1], "Y_pattern": [313, 362], "supp": 179, "conf": 0.02080306816200825}, {"X_pattern": [-1], "Y_pattern": [237, 473], "supp": 168, "conf": 0.019524667325236795}, {"X_pattern": [-1], "Y_pattern": [247, 471], "supp": 171, "conf": 0.019873322098901736}, {"X_pattern": [-1], "Y_pattern": [281, 387], "supp": 164, "conf": 0.019059794293683537}, {"X_pattern": [-1], "Y_pattern": [15, 256], "supp": 168, "conf": 0.019524667325236795}, {"X_pattern": [-1], "Y_pattern": [35, 150], "supp": 165, "conf": 0.019176012551571853}, {"X_pattern": [-1], "Y_pattern": [10, 154], "supp": 161, "conf": 0.018711139520018596}, {"X_pattern": [-1], "Y_pattern": [309, 470], "supp": 158, "conf": 0.01836248474635365}, {"X_pattern": [-1], "Y_pattern": [63, 147], "supp": 148, "conf": 0.01720030216747051}, {"X_pattern": [-1], "Y_pattern": [70, 106], "supp": 150, "conf": 0.01743273868324714}, {"X_pattern": [-1], "Y_pattern": [129, 227], "supp": 153, "conf": 0.01778139345691208}, {"X_pattern": [-1], "Y_pattern": [297, 340], "supp": 159, "conf": 0.018478703004241967}, {"X_pattern": [-1], "Y_pattern": [248, 364], "supp": 119, "conf": 0.013829972688709396}, {"X_pattern": [-1], "Y_pattern": [104, 169], "supp": 149, "conf": 0.017316520425358823}, {"X_pattern": [-1], "Y_pattern": [36, 134], "supp": 152, "conf": 0.017665175199023768}, {"X_pattern": [-1], "Y_pattern": [8, 41], "supp": 148, "conf": 0.01720030216747051}, {"X_pattern": [-1], "Y_pattern": [346, 443], "supp": 148, "conf": 0.01720030216747051}, {"X_pattern": [-1], "Y_pattern": [95, 244], "supp": 146, "conf": 0.01696786565169388}, {"X_pattern": [-1], "Y_pattern": [324, 437], "supp": 120, "conf": 0.01394619094659771}, {"X_pattern": [-1], "Y_pattern": [103, 477], "supp": 132, "conf": 0.015340810041257482}], "total_encoding_cost": 153660.00299205806, "precision": 0.4440789473684211, "recall": 0.84375, "F1": 0.5818965517241379}