{"model": [{"X_pattern": [-1], "Y_pattern": [395, 716, 957, 1069]}, {"X_pattern": [-1], "Y_pattern": [713, 964, 162, 172, 1005]}, {"X_pattern": [-1], "Y_pattern": [380, 395, 716, 957, 1069]}, {"X_pattern": [-1], "Y_pattern": [816, 983, 435, 759, 1059]}, {"X_pattern": [-1], "Y_pattern": [504, 889, 813, 829, 1064]}, {"X_pattern": [-1], "Y_pattern": [4, 734, 315, 790, 867]}, {"X_pattern": [-1], "Y_pattern": [525, 805, 927, 966, 1087]}, {"X_pattern": [-1], "Y_pattern": [827, 1065, 636, 801, 872]}, {"X_pattern": [-1], "Y_pattern": [587, 603, 520, 750, 832]}, {"X_pattern": [-1], "Y_pattern": [127, 552, 448, 937, 1036]}, {"X_pattern": [-1], "Y_pattern": [275, 377, 864, 989, 1090]}, {"X_pattern": [-1], "Y_pattern": [816, 983]}, {"X_pattern": [-1], "Y_pattern": [504, 889]}, {"X_pattern": [-1], "Y_pattern": [805, 927, 966, 1087]}, {"X_pattern": [-1], "Y_pattern": [127, 552]}, {"X_pattern": [-1], "Y_pattern": [1065, 636, 801, 872]}, {"X_pattern": [-1], "Y_pattern": [552, 448, 937, 1036]}, {"X_pattern": [-1], "Y_pattern": [603, 520, 750, 832]}, {"X_pattern": [-1], "Y_pattern": [827, 1065]}, {"X_pattern": [-1], "Y_pattern": [4, 734]}, {"X_pattern": [-1], "Y_pattern": [964, 162, 172, 1005]}, {"X_pattern": [-1], "Y_pattern": [587, 603]}, {"X_pattern": [-1], "Y_pattern": [380, 395]}, {"X_pattern": [-1], "Y_pattern": [983, 435, 759, 1059]}, {"X_pattern": [-1], "Y_pattern": [275, 377]}, {"X_pattern": [-1], "Y_pattern": [377, 864, 989, 1090]}, {"X_pattern": [-1], "Y_pattern": [713, 964]}, {"X_pattern": [-1], "Y_pattern": [864, 989, 1090]}, {"X_pattern": [-1], "Y_pattern": [435, 759, 1059]}, {"X_pattern": [-1], "Y_pattern": [525, 805]}, {"X_pattern": [-1], "Y_pattern": [889, 813, 829, 1064]}, {"X_pattern": [-1], "Y_pattern": [636, 801, 872]}, {"X_pattern": [-1], "Y_pattern": [813, 829, 1064]}, {"X_pattern": [-1], "Y_pattern": [520, 750, 832]}, {"X_pattern": [-1], "Y_pattern": [162, 172, 1005]}, {"X_pattern": [-1], "Y_pattern": [734, 315, 790, 867]}, {"X_pattern": [-1], "Y_pattern": [315, 790, 867]}, {"X_pattern": [-1], "Y_pattern": [448, 937, 1036]}, {"X_pattern": [-1], "Y_pattern": [927, 966, 1087]}, {"X_pattern": [-1], "Y_pattern": [759, 1059]}, {"X_pattern": [-1], "Y_pattern": [801, 872]}, {"X_pattern": [-1], "Y_pattern": [989, 1090]}, {"X_pattern": [-1], "Y_pattern": [636, 801]}, {"X_pattern": [-1], "Y_pattern": [966, 1087]}, {"X_pattern": [-1], "Y_pattern": [790, 867]}, {"X_pattern": [-1], "Y_pattern": [937, 1036]}], "precision": 0.36684782608695654, "recall": 0.84375, "F1": 0.5113636363636364}