{"model": [{"X_pattern": [26], "Y_pattern": [81]}, {"X_pattern": [2], "Y_pattern": [202]}, {"X_pattern": [87], "Y_pattern": [355]}, {"X_pattern": [41], "Y_pattern": [400]}, {"X_pattern": [233], "Y_pattern": [336]}, {"X_pattern": [234], "Y_pattern": [282]}, {"X_pattern": [46], "Y_pattern": [73]}, {"X_pattern": [74], "Y_pattern": [479]}, {"X_pattern": [416], "Y_pattern": [444]}, {"X_pattern": [243], "Y_pattern": [423]}, {"X_pattern": [210], "Y_pattern": [316]}, {"X_pattern": [81], "Y_pattern": [99]}, {"X_pattern": [35], "Y_pattern": [58]}, {"X_pattern": [336], "Y_pattern": [26]}, {"X_pattern": [413], "Y_pattern": [471]}, {"X_pattern": [282], "Y_pattern": [360]}, {"X_pattern": [58], "Y_pattern": [445]}, {"X_pattern": [26, 336], "Y_pattern": [81]}, {"X_pattern": [336], "Y_pattern": [26, 81]}, {"X_pattern": [336], "Y_pattern": [81]}, {"X_pattern": [155], "Y_pattern": [270]}], "precision": 0.5568594104308392, "recall": 0.5802380952380952, "F1": 0.5683084203649155}