{"model": [{"X_pattern": [11], "Y_pattern": [589]}, {"X_pattern": [11], "Y_pattern": [589, 874]}, {"X_pattern": [11], "Y_pattern": [874]}, {"X_pattern": [46], "Y_pattern": [662]}, {"X_pattern": [46], "Y_pattern": [378]}, {"X_pattern": [46], "Y_pattern": [378, 662]}, {"X_pattern": [66], "Y_pattern": [676]}, {"X_pattern": [66], "Y_pattern": [607]}, {"X_pattern": [66], "Y_pattern": [607, 676]}, {"X_pattern": [141], "Y_pattern": [468]}, {"X_pattern": [141], "Y_pattern": [468, 596]}, {"X_pattern": [141], "Y_pattern": [596]}, {"X_pattern": [148], "Y_pattern": [417]}, {"X_pattern": [148], "Y_pattern": [347]}, {"X_pattern": [148], "Y_pattern": [347, 417]}, {"X_pattern": [167], "Y_pattern": [676, 849]}, {"X_pattern": [167], "Y_pattern": [66, 849]}, {"X_pattern": [167], "Y_pattern": [66, 607, 849]}, {"X_pattern": [167], "Y_pattern": [66, 676, 849]}, {"X_pattern": [167], "Y_pattern": [66, 607, 676, 849]}, {"X_pattern": [167], "Y_pattern": [849]}, {"X_pattern": [167], "Y_pattern": [607, 849]}, {"X_pattern": [167], "Y_pattern": [607, 676, 849]}, {"X_pattern": [168], "Y_pattern": [710]}, {"X_pattern": [168], "Y_pattern": [601]}, {"X_pattern": [168], "Y_pattern": [601, 710]}, {"X_pattern": [207], "Y_pattern": [148, 470]}, {"X_pattern": [207], "Y_pattern": [148, 347, 470]}, {"X_pattern": [207], "Y_pattern": [470]}, {"X_pattern": [207], "Y_pattern": [347, 470]}, {"X_pattern": [221], "Y_pattern": [276]}, {"X_pattern": [221], "Y_pattern": [243]}, {"X_pattern": [221], "Y_pattern": [243, 276]}, {"X_pattern": [240], "Y_pattern": [789]}, {"X_pattern": [240], "Y_pattern": [789, 837]}, {"X_pattern": [240], "Y_pattern": [534, 789]}, {"X_pattern": [240], "Y_pattern": [534, 709, 789]}, {"X_pattern": [240], "Y_pattern": [534, 789, 837]}, {"X_pattern": [240], "Y_pattern": [534, 709, 789, 837]}, {"X_pattern": [240], "Y_pattern": [709, 789]}, {"X_pattern": [240], "Y_pattern": [709, 789, 837]}, {"X_pattern": [243], "Y_pattern": [276]}, {"X_pattern": [266], "Y_pattern": [141, 823]}, {"X_pattern": [266], "Y_pattern": [141, 468, 823]}, {"X_pattern": [266], "Y_pattern": [141, 596, 823]}, {"X_pattern": [266], "Y_pattern": [141, 468, 596, 823]}, {"X_pattern": [266], "Y_pattern": [823]}, {"X_pattern": [266], "Y_pattern": [468, 823]}, {"X_pattern": [266], "Y_pattern": [468, 596, 823]}, {"X_pattern": [266], "Y_pattern": [596, 823]}, {"X_pattern": [301], "Y_pattern": [821]}, {"X_pattern": [301], "Y_pattern": [728]}, {"X_pattern": [301], "Y_pattern": [728, 821]}, {"X_pattern": [334], "Y_pattern": [631]}, {"X_pattern": [347], "Y_pattern": [417]}, {"X_pattern": [352], "Y_pattern": [168, 859]}, {"X_pattern": [352], "Y_pattern": [168, 710, 859]}, {"X_pattern": [352], "Y_pattern": [168, 601, 859]}, {"X_pattern": [352], "Y_pattern": [168, 601, 710, 859]}, {"X_pattern": [352], "Y_pattern": [710, 859]}, {"X_pattern": [352], "Y_pattern": [601, 859]}, {"X_pattern": [352], "Y_pattern": [601, 710, 859]}, {"X_pattern": [352], "Y_pattern": [859]}, {"X_pattern": [378], "Y_pattern": [662]}, {"X_pattern": [385], "Y_pattern": [448]}, {"X_pattern": [385], "Y_pattern": [448, 715]}, {"X_pattern": [385], "Y_pattern": [448, 716]}, {"X_pattern": [385], "Y_pattern": [448, 715, 716]}, {"X_pattern": [448], "Y_pattern": [715]}, {"X_pattern": [448], "Y_pattern": [715, 742]}, {"X_pattern": [448], "Y_pattern": [715, 716]}, {"X_pattern": [448], "Y_pattern": [715, 716, 742]}, {"X_pattern": [448], "Y_pattern": [716]}, {"X_pattern": [448], "Y_pattern": [716, 742]}, {"X_pattern": [454], "Y_pattern": [461]}, {"X_pattern": [468], "Y_pattern": [596]}, {"X_pattern": [470], "Y_pattern": [148]}, {"X_pattern": [470], "Y_pattern": [148, 347]}, {"X_pattern": [470], "Y_pattern": [148, 417]}, {"X_pattern": [470], "Y_pattern": [148, 347, 417]}, {"X_pattern": [470], "Y_pattern": [347]}, {"X_pattern": [470], "Y_pattern": [347, 417]}, {"X_pattern": [473], "Y_pattern": [608]}, {"X_pattern": [534], "Y_pattern": [709]}, {"X_pattern": [534], "Y_pattern": [709, 837]}, {"X_pattern": [534], "Y_pattern": [837]}, {"X_pattern": [553], "Y_pattern": [276, 679]}, {"X_pattern": [553], "Y_pattern": [679]}, {"X_pattern": [553], "Y_pattern": [221, 679]}, {"X_pattern": [553], "Y_pattern": [221, 276, 679]}, {"X_pattern": [553], "Y_pattern": [221, 243, 679]}, {"X_pattern": [553], "Y_pattern": [221, 243, 276, 679]}, {"X_pattern": [553], "Y_pattern": [243, 679]}, {"X_pattern": [553], "Y_pattern": [243, 276, 679]}, {"X_pattern": [589], "Y_pattern": [874]}, {"X_pattern": [601], "Y_pattern": [710]}, {"X_pattern": [607], "Y_pattern": [676]}, {"X_pattern": [608], "Y_pattern": [11]}, {"X_pattern": [608], "Y_pattern": [11, 589]}, {"X_pattern": [608], "Y_pattern": [11, 874]}, {"X_pattern": [608], "Y_pattern": [11, 589, 874]}, {"X_pattern": [679], "Y_pattern": [276]}, {"X_pattern": [679], "Y_pattern": [221]}, {"X_pattern": [679], "Y_pattern": [221, 276]}, {"X_pattern": [679], "Y_pattern": [221, 243]}, {"X_pattern": [679], "Y_pattern": [221, 243, 276]}, {"X_pattern": [679], "Y_pattern": [243]}, {"X_pattern": [679], "Y_pattern": [243, 276]}, {"X_pattern": [709], "Y_pattern": [837]}, {"X_pattern": [715], "Y_pattern": [716]}, {"X_pattern": [715], "Y_pattern": [716, 742]}, {"X_pattern": [715], "Y_pattern": [742]}, {"X_pattern": [716], "Y_pattern": [742]}, {"X_pattern": [728], "Y_pattern": [821]}, {"X_pattern": [789], "Y_pattern": [534]}, {"X_pattern": [789], "Y_pattern": [534, 709]}, {"X_pattern": [789], "Y_pattern": [534, 837]}, {"X_pattern": [789], "Y_pattern": [534, 709, 837]}, {"X_pattern": [789], "Y_pattern": [709]}, {"X_pattern": [789], "Y_pattern": [709, 837]}, {"X_pattern": [789], "Y_pattern": [837]}, {"X_pattern": [823], "Y_pattern": [141]}, {"X_pattern": [823], "Y_pattern": [141, 468]}, {"X_pattern": [823], "Y_pattern": [141, 596]}, {"X_pattern": [823], "Y_pattern": [141, 468, 596]}, {"X_pattern": [823], "Y_pattern": [468]}, {"X_pattern": [823], "Y_pattern": [468, 596]}, {"X_pattern": [849], "Y_pattern": [676]}, {"X_pattern": [849], "Y_pattern": [66]}, {"X_pattern": [849], "Y_pattern": [66, 607]}, {"X_pattern": [849], "Y_pattern": [66, 676]}, {"X_pattern": [849], "Y_pattern": [66, 607, 676]}, {"X_pattern": [849], "Y_pattern": [607]}, {"X_pattern": [849], "Y_pattern": [607, 676]}, {"X_pattern": [859], "Y_pattern": [168]}, {"X_pattern": [859], "Y_pattern": [168, 710]}, {"X_pattern": [859], "Y_pattern": [168, 601]}, {"X_pattern": [859], "Y_pattern": [168, 601, 710]}, {"X_pattern": [859], "Y_pattern": [710]}, {"X_pattern": [859], "Y_pattern": [601]}, {"X_pattern": [859], "Y_pattern": [601, 710]}, {"X_pattern": [11, 473], "Y_pattern": [589]}, {"X_pattern": [11, 473], "Y_pattern": [589, 874]}, {"X_pattern": [11, 473], "Y_pattern": [874]}, {"X_pattern": [11, 589], "Y_pattern": [874]}, {"X_pattern": [11, 608], "Y_pattern": [589]}, {"X_pattern": [11, 608], "Y_pattern": [589, 874]}, {"X_pattern": [11, 608], "Y_pattern": [874]}, {"X_pattern": [46, 378], "Y_pattern": [662]}, {"X_pattern": [46, 631], "Y_pattern": [662]}, {"X_pattern": [46, 631], "Y_pattern": [378]}, {"X_pattern": [46, 631], "Y_pattern": [378, 662]}, {"X_pattern": [66, 607], "Y_pattern": [676]}, {"X_pattern": [66, 849], "Y_pattern": [676]}, {"X_pattern": [66, 849], "Y_pattern": [607]}, {"X_pattern": [66, 849], "Y_pattern": [607, 676]}, {"X_pattern": [141, 266], "Y_pattern": [468]}, {"X_pattern": [141, 266], "Y_pattern": [468, 596]}, {"X_pattern": [141, 266], "Y_pattern": [596]}, {"X_pattern": [141, 468], "Y_pattern": [596]}, {"X_pattern": [141, 823], "Y_pattern": [468]}, {"X_pattern": [141, 823], "Y_pattern": [468, 596]}, {"X_pattern": [141, 823], "Y_pattern": [596]}, {"X_pattern": [148, 347], "Y_pattern": [417]}, {"X_pattern": [148, 470], "Y_pattern": [417]}, {"X_pattern": [148, 470], "Y_pattern": [347]}, {"X_pattern": [148, 470], "Y_pattern": [347, 417]}, {"X_pattern": [167, 849], "Y_pattern": [676]}, {"X_pattern": [167, 849], "Y_pattern": [66]}, {"X_pattern": [167, 849], "Y_pattern": [66, 607]}, {"X_pattern": [167, 849], "Y_pattern": [66, 676]}, {"X_pattern": [167, 849], "Y_pattern": [66, 607, 676]}, {"X_pattern": [167, 849], "Y_pattern": [607]}, {"X_pattern": [167, 849], "Y_pattern": [607, 676]}, {"X_pattern": [168, 601], "Y_pattern": [710]}, {"X_pattern": [168, 859], "Y_pattern": [710]}, {"X_pattern": [168, 859], "Y_pattern": [601]}, {"X_pattern": [168, 859], "Y_pattern": [601, 710]}, {"X_pattern": [207, 470], "Y_pattern": [148]}, {"X_pattern": [207, 470], "Y_pattern": [148, 347]}, {"X_pattern": [207, 470], "Y_pattern": [148, 417]}, {"X_pattern": [207, 470], "Y_pattern": [148, 347, 417]}, {"X_pattern": [207, 470], "Y_pattern": [417]}, {"X_pattern": [207, 470], "Y_pattern": [347]}, {"X_pattern": [207, 470], "Y_pattern": [347, 417]}, {"X_pattern": [221, 243], "Y_pattern": [276]}, {"X_pattern": [221, 553], "Y_pattern": [276]}, {"X_pattern": [221, 553], "Y_pattern": [243]}, {"X_pattern": [221, 553], "Y_pattern": [243, 276]}, {"X_pattern": [221, 679], "Y_pattern": [276]}, {"X_pattern": [221, 679], "Y_pattern": [243]}, {"X_pattern": [221, 679], "Y_pattern": [243, 276]}, {"X_pattern": [240, 534], "Y_pattern": [709]}, {"X_pattern": [240, 534], "Y_pattern": [709, 837]}, {"X_pattern": [240, 534], "Y_pattern": [837]}, {"X_pattern": [240, 789], "Y_pattern": [534]}, {"X_pattern": [240, 789], "Y_pattern": [534, 709]}, {"X_pattern": [240, 789], "Y_pattern": [534, 837]}, {"X_pattern": [240, 789], "Y_pattern": [534, 709, 837]}, {"X_pattern": [240, 789], "Y_pattern": [709]}, {"X_pattern": [240, 789], "Y_pattern": [709, 837]}, {"X_pattern": [240, 789], "Y_pattern": [837]}, {"X_pattern": [243, 679], "Y_pattern": [276]}, {"X_pattern": [266, 823], "Y_pattern": [141]}, {"X_pattern": [266, 823], "Y_pattern": [141, 468]}, {"X_pattern": [266, 823], "Y_pattern": [141, 596]}, {"X_pattern": [266, 823], "Y_pattern": [141, 468, 596]}, {"X_pattern": [266, 823], "Y_pattern": [468]}, {"X_pattern": [266, 823], "Y_pattern": [468, 596]}, {"X_pattern": [266, 823], "Y_pattern": [596]}, {"X_pattern": [301, 461], "Y_pattern": [821]}, {"X_pattern": [301, 461], "Y_pattern": [728]}, {"X_pattern": [301, 461], "Y_pattern": [728, 821]}, {"X_pattern": [301, 728], "Y_pattern": [821]}, {"X_pattern": [334, 631], "Y_pattern": [662]}, {"X_pattern": [334, 631], "Y_pattern": [46]}, {"X_pattern": [334, 631], "Y_pattern": [46, 662]}, {"X_pattern": [334, 631], "Y_pattern": [46, 378]}, {"X_pattern": [334, 631], "Y_pattern": [46, 378, 662]}, {"X_pattern": [334, 631], "Y_pattern": [378]}, {"X_pattern": [334, 631], "Y_pattern": [378, 662]}, {"X_pattern": [347, 470], "Y_pattern": [417]}, {"X_pattern": [352, 859], "Y_pattern": [168]}, {"X_pattern": [352, 859], "Y_pattern": [168, 710]}, {"X_pattern": [352, 859], "Y_pattern": [168, 601]}, {"X_pattern": [352, 859], "Y_pattern": [168, 601, 710]}, {"X_pattern": [352, 859], "Y_pattern": [710]}, {"X_pattern": [352, 859], "Y_pattern": [601]}, {"X_pattern": [352, 859], "Y_pattern": [601, 710]}, {"X_pattern": [378, 631], "Y_pattern": [662]}, {"X_pattern": [385, 448], "Y_pattern": [715]}, {"X_pattern": [385, 448], "Y_pattern": [715, 742]}, {"X_pattern": [385, 448], "Y_pattern": [715, 716]}, {"X_pattern": [385, 448], "Y_pattern": [715, 716, 742]}, {"X_pattern": [385, 448], "Y_pattern": [716]}, {"X_pattern": [385, 448], "Y_pattern": [716, 742]}, {"X_pattern": [385, 448], "Y_pattern": [742]}, {"X_pattern": [448, 715], "Y_pattern": [716]}, {"X_pattern": [448, 715], "Y_pattern": [716, 742]}, {"X_pattern": [448, 715], "Y_pattern": [742]}, {"X_pattern": [448, 716], "Y_pattern": [742]}, {"X_pattern": [454, 461], "Y_pattern": [301]}, {"X_pattern": [454, 461], "Y_pattern": [301, 728]}, {"X_pattern": [454, 461], "Y_pattern": [301, 821]}, {"X_pattern": [454, 461], "Y_pattern": [301, 728, 821]}, {"X_pattern": [454, 461], "Y_pattern": [728]}, {"X_pattern": [454, 461], "Y_pattern": [728, 821]}, {"X_pattern": [468, 823], "Y_pattern": [596]}, {"X_pattern": [473, 608], "Y_pattern": [11]}, {"X_pattern": [473, 608], "Y_pattern": [11, 589]}, {"X_pattern": [473, 608], "Y_pattern": [11, 874]}, {"X_pattern": [473, 608], "Y_pattern": [11, 589, 874]}, {"X_pattern": [473, 608], "Y_pattern": [589]}, {"X_pattern": [473, 608], "Y_pattern": [589, 874]}, {"X_pattern": [473, 608], "Y_pattern": [874]}, {"X_pattern": [534, 709], "Y_pattern": [837]}, {"X_pattern": [534, 789], "Y_pattern": [709]}, {"X_pattern": [534, 789], "Y_pattern": [709, 837]}, {"X_pattern": [534, 789], "Y_pattern": [837]}, {"X_pattern": [553, 679], "Y_pattern": [276]}, {"X_pattern": [553, 679], "Y_pattern": [221]}, {"X_pattern": [553, 679], "Y_pattern": [221, 276]}, {"X_pattern": [553, 679], "Y_pattern": [221, 243]}, {"X_pattern": [553, 679], "Y_pattern": [221, 243, 276]}, {"X_pattern": [553, 679], "Y_pattern": [243]}, {"X_pattern": [553, 679], "Y_pattern": [243, 276]}, {"X_pattern": [589, 608], "Y_pattern": [874]}, {"X_pattern": [601, 859], "Y_pattern": [710]}, {"X_pattern": [607, 849], "Y_pattern": [676]}, {"X_pattern": [709, 789], "Y_pattern": [837]}, {"X_pattern": [715, 716], "Y_pattern": [742]}, {"X_pattern": [11, 473, 608], "Y_pattern": [589]}, {"X_pattern": [11, 473, 608], "Y_pattern": [589, 874]}, {"X_pattern": [11, 473, 608], "Y_pattern": [874]}, {"X_pattern": [11, 589, 608], "Y_pattern": [874]}, {"X_pattern": [46, 378, 631], "Y_pattern": [662]}, {"X_pattern": [66, 607, 849], "Y_pattern": [676]}, {"X_pattern": [141, 468, 823], "Y_pattern": [596]}, {"X_pattern": [148, 347, 470], "Y_pattern": [417]}, {"X_pattern": [168, 601, 859], "Y_pattern": [710]}, {"X_pattern": [221, 243, 679], "Y_pattern": [276]}, {"X_pattern": [221, 553, 679], "Y_pattern": [276]}, {"X_pattern": [221, 553, 679], "Y_pattern": [243]}, {"X_pattern": [221, 553, 679], "Y_pattern": [243, 276]}, {"X_pattern": [240, 534, 789], "Y_pattern": [709]}, {"X_pattern": [240, 534, 789], "Y_pattern": [709, 837]}, {"X_pattern": [240, 534, 789], "Y_pattern": [837]}, {"X_pattern": [448, 715, 716], "Y_pattern": [742]}, {"X_pattern": [534, 709, 789], "Y_pattern": [837]}], "precision": 0.06555171088043062, "recall": 0.8333333333333333, "F1": 0.12154262902765899}