{"model": [{"X_pattern": [1], "Y_pattern": [29]}, {"X_pattern": [1], "Y_pattern": [29, 180]}, {"X_pattern": [1], "Y_pattern": [180]}, {"X_pattern": [12], "Y_pattern": [62]}, {"X_pattern": [12], "Y_pattern": [62, 113]}, {"X_pattern": [12], "Y_pattern": [113]}, {"X_pattern": [14], "Y_pattern": [169]}, {"X_pattern": [14], "Y_pattern": [169, 248]}, {"X_pattern": [14], "Y_pattern": [83]}, {"X_pattern": [14], "Y_pattern": [83, 169]}, {"X_pattern": [14], "Y_pattern": [83, 106]}, {"X_pattern": [14], "Y_pattern": [83, 248]}, {"X_pattern": [14], "Y_pattern": [83, 169, 248]}, {"X_pattern": [14], "Y_pattern": [83, 106, 169]}, {"X_pattern": [14], "Y_pattern": [83, 106, 248]}, {"X_pattern": [14], "Y_pattern": [83, 106, 169, 248]}, {"X_pattern": [14], "Y_pattern": [106]}, {"X_pattern": [14], "Y_pattern": [106, 169]}, {"X_pattern": [14], "Y_pattern": [106, 248]}, {"X_pattern": [14], "Y_pattern": [106, 169, 248]}, {"X_pattern": [14], "Y_pattern": [248]}, {"X_pattern": [17], "Y_pattern": [31]}, {"X_pattern": [17], "Y_pattern": [31, 67]}, {"X_pattern": [17], "Y_pattern": [31, 234]}, {"X_pattern": [17], "Y_pattern": [31, 298]}, {"X_pattern": [17], "Y_pattern": [31, 67, 234]}, {"X_pattern": [17], "Y_pattern": [31, 67, 298]}, {"X_pattern": [17], "Y_pattern": [31, 234, 298]}, {"X_pattern": [17], "Y_pattern": [31, 67, 234, 298]}, {"X_pattern": [17], "Y_pattern": [298]}, {"X_pattern": [17], "Y_pattern": [67]}, {"X_pattern": [17], "Y_pattern": [67, 234]}, {"X_pattern": [17], "Y_pattern": [67, 298]}, {"X_pattern": [17], "Y_pattern": [67, 234, 298]}, {"X_pattern": [17], "Y_pattern": [234]}, {"X_pattern": [17], "Y_pattern": [234, 298]}, {"X_pattern": [27], "Y_pattern": [1]}, {"X_pattern": [27], "Y_pattern": [1, 29]}, {"X_pattern": [27], "Y_pattern": [1, 180]}, {"X_pattern": [27], "Y_pattern": [1, 122]}, {"X_pattern": [27], "Y_pattern": [1, 29, 180]}, {"X_pattern": [27], "Y_pattern": [1, 29, 122]}, {"X_pattern": [27], "Y_pattern": [1, 122, 180]}, {"X_pattern": [27], "Y_pattern": [1, 29, 122, 180]}, {"X_pattern": [27], "Y_pattern": [29]}, {"X_pattern": [27], "Y_pattern": [29, 180]}, {"X_pattern": [27], "Y_pattern": [29, 122]}, {"X_pattern": [27], "Y_pattern": [29, 122, 180]}, {"X_pattern": [27], "Y_pattern": [180]}, {"X_pattern": [27], "Y_pattern": [122]}, {"X_pattern": [27], "Y_pattern": [122, 180]}, {"X_pattern": [29], "Y_pattern": [180]}, {"X_pattern": [31], "Y_pattern": [298]}, {"X_pattern": [31], "Y_pattern": [234]}, {"X_pattern": [31], "Y_pattern": [234, 298]}, {"X_pattern": [33], "Y_pattern": [266]}, {"X_pattern": [33], "Y_pattern": [203]}, {"X_pattern": [33], "Y_pattern": [203, 266]}, {"X_pattern": [37], "Y_pattern": [259]}, {"X_pattern": [37], "Y_pattern": [238]}, {"X_pattern": [37], "Y_pattern": [238, 259]}, {"X_pattern": [42], "Y_pattern": [155]}, {"X_pattern": [42], "Y_pattern": [126]}, {"X_pattern": [42], "Y_pattern": [126, 155]}, {"X_pattern": [45], "Y_pattern": [155]}, {"X_pattern": [45], "Y_pattern": [42]}, {"X_pattern": [45], "Y_pattern": [42, 155]}, {"X_pattern": [45], "Y_pattern": [42, 58]}, {"X_pattern": [45], "Y_pattern": [42, 126]}, {"X_pattern": [45], "Y_pattern": [42, 58, 155]}, {"X_pattern": [45], "Y_pattern": [42, 58, 126]}, {"X_pattern": [45], "Y_pattern": [42, 126, 155]}, {"X_pattern": [45], "Y_pattern": [42, 58, 126, 155]}, {"X_pattern": [45], "Y_pattern": [58]}, {"X_pattern": [45], "Y_pattern": [58, 155]}, {"X_pattern": [45], "Y_pattern": [58, 126]}, {"X_pattern": [45], "Y_pattern": [58, 126, 155]}, {"X_pattern": [45], "Y_pattern": [126]}, {"X_pattern": [45], "Y_pattern": [126, 155]}, {"X_pattern": [56], "Y_pattern": [178]}, {"X_pattern": [56], "Y_pattern": [178, 227]}, {"X_pattern": [56], "Y_pattern": [227]}, {"X_pattern": [58], "Y_pattern": [155]}, {"X_pattern": [58], "Y_pattern": [42]}, {"X_pattern": [58], "Y_pattern": [42, 155]}, {"X_pattern": [58], "Y_pattern": [42, 126]}, {"X_pattern": [58], "Y_pattern": [42, 126, 155]}, {"X_pattern": [58], "Y_pattern": [126]}, {"X_pattern": [58], "Y_pattern": [126, 155]}, {"X_pattern": [62], "Y_pattern": [113]}, {"X_pattern": [64], "Y_pattern": [296]}, {"X_pattern": [64], "Y_pattern": [69]}, {"X_pattern": [64], "Y_pattern": [69, 76]}, {"X_pattern": [64], "Y_pattern": [69, 79]}, {"X_pattern": [64], "Y_pattern": [69, 296]}, {"X_pattern": [64], "Y_pattern": [69, 76, 79]}, {"X_pattern": [64], "Y_pattern": [69, 76, 296]}, {"X_pattern": [64], "Y_pattern": [69, 79, 296]}, {"X_pattern": [64], "Y_pattern": [69, 76, 79, 296]}, {"X_pattern": [64], "Y_pattern": [76]}, {"X_pattern": [64], "Y_pattern": [76, 79]}, {"X_pattern": [64], "Y_pattern": [76, 296]}, {"X_pattern": [64], "Y_pattern": [76, 79, 296]}, {"X_pattern": [64], "Y_pattern": [79]}, {"X_pattern": [64], "Y_pattern": [79, 296]}, {"X_pattern": [67], "Y_pattern": [31]}, {"X_pattern": [67], "Y_pattern": [31, 234]}, {"X_pattern": [67], "Y_pattern": [31, 298]}, {"X_pattern": [67], "Y_pattern": [31, 234, 298]}, {"X_pattern": [67], "Y_pattern": [298]}, {"X_pattern": [67], "Y_pattern": [234]}, {"X_pattern": [67], "Y_pattern": [234, 298]}, {"X_pattern": [69], "Y_pattern": [296]}, {"X_pattern": [69], "Y_pattern": [76]}, {"X_pattern": [69], "Y_pattern": [76, 296]}, {"X_pattern": [76], "Y_pattern": [296]}, {"X_pattern": [79], "Y_pattern": [296]}, {"X_pattern": [79], "Y_pattern": [69]}, {"X_pattern": [79], "Y_pattern": [69, 76]}, {"X_pattern": [79], "Y_pattern": [69, 296]}, {"X_pattern": [79], "Y_pattern": [69, 76, 296]}, {"X_pattern": [79], "Y_pattern": [76]}, {"X_pattern": [79], "Y_pattern": [76, 296]}, {"X_pattern": [83], "Y_pattern": [169]}, {"X_pattern": [83], "Y_pattern": [169, 248]}, {"X_pattern": [83], "Y_pattern": [106]}, {"X_pattern": [83], "Y_pattern": [106, 169]}, {"X_pattern": [83], "Y_pattern": [106, 248]}, {"X_pattern": [83], "Y_pattern": [106, 169, 248]}, {"X_pattern": [83], "Y_pattern": [248]}, {"X_pattern": [84], "Y_pattern": [12]}, {"X_pattern": [84], "Y_pattern": [12, 157]}, {"X_pattern": [84], "Y_pattern": [12, 113]}, {"X_pattern": [84], "Y_pattern": [12, 62]}, {"X_pattern": [84], "Y_pattern": [12, 113, 157]}, {"X_pattern": [84], "Y_pattern": [12, 62, 157]}, {"X_pattern": [84], "Y_pattern": [12, 62, 113]}, {"X_pattern": [84], "Y_pattern": [12, 62, 113, 157]}, {"X_pattern": [84], "Y_pattern": [157]}, {"X_pattern": [84], "Y_pattern": [62]}, {"X_pattern": [84], "Y_pattern": [62, 157]}, {"X_pattern": [84], "Y_pattern": [62, 113]}, {"X_pattern": [84], "Y_pattern": [62, 113, 157]}, {"X_pattern": [84], "Y_pattern": [113]}, {"X_pattern": [84], "Y_pattern": [113, 157]}, {"X_pattern": [93], "Y_pattern": [204]}, {"X_pattern": [93], "Y_pattern": [204, 252]}, {"X_pattern": [93], "Y_pattern": [204, 222]}, {"X_pattern": [93], "Y_pattern": [204, 222, 252]}, {"X_pattern": [93], "Y_pattern": [222]}, {"X_pattern": [93], "Y_pattern": [222, 252]}, {"X_pattern": [93], "Y_pattern": [100]}, {"X_pattern": [93], "Y_pattern": [100, 204]}, {"X_pattern": [93], "Y_pattern": [100, 222]}, {"X_pattern": [93], "Y_pattern": [100, 252]}, {"X_pattern": [93], "Y_pattern": [100, 204, 222]}, {"X_pattern": [93], "Y_pattern": [100, 204, 252]}, {"X_pattern": [93], "Y_pattern": [100, 222, 252]}, {"X_pattern": [93], "Y_pattern": [100, 204, 222, 252]}, {"X_pattern": [93], "Y_pattern": [252]}, {"X_pattern": [100], "Y_pattern": [204]}, {"X_pattern": [100], "Y_pattern": [204, 222]}, {"X_pattern": [100], "Y_pattern": [222]}, {"X_pattern": [102], "Y_pattern": [266]}, {"X_pattern": [102], "Y_pattern": [33]}, {"X_pattern": [102], "Y_pattern": [33, 266]}, {"X_pattern": [102], "Y_pattern": [33, 203]}, {"X_pattern": [102], "Y_pattern": [33, 120]}, {"X_pattern": [102], "Y_pattern": [33, 203, 266]}, {"X_pattern": [102], "Y_pattern": [33, 120, 266]}, {"X_pattern": [102], "Y_pattern": [33, 120, 203]}, {"X_pattern": [102], "Y_pattern": [33, 120, 203, 266]}, {"X_pattern": [102], "Y_pattern": [203]}, {"X_pattern": [102], "Y_pattern": [203, 266]}, {"X_pattern": [102], "Y_pattern": [120]}, {"X_pattern": [102], "Y_pattern": [120, 266]}, {"X_pattern": [102], "Y_pattern": [120, 203]}, {"X_pattern": [102], "Y_pattern": [120, 203, 266]}, {"X_pattern": [106], "Y_pattern": [169]}, {"X_pattern": [106], "Y_pattern": [169, 248]}, {"X_pattern": [106], "Y_pattern": [248]}, {"X_pattern": [120], "Y_pattern": [266]}, {"X_pattern": [120], "Y_pattern": [33]}, {"X_pattern": [120], "Y_pattern": [33, 266]}, {"X_pattern": [120], "Y_pattern": [33, 203]}, {"X_pattern": [120], "Y_pattern": [33, 203, 266]}, {"X_pattern": [120], "Y_pattern": [203]}, {"X_pattern": [120], "Y_pattern": [203, 266]}, {"X_pattern": [122], "Y_pattern": [1]}, {"X_pattern": [122], "Y_pattern": [1, 29]}, {"X_pattern": [122], "Y_pattern": [1, 180]}, {"X_pattern": [122], "Y_pattern": [1, 29, 180]}, {"X_pattern": [122], "Y_pattern": [29]}, {"X_pattern": [122], "Y_pattern": [29, 180]}, {"X_pattern": [122], "Y_pattern": [180]}, {"X_pattern": [126], "Y_pattern": [155]}, {"X_pattern": [147], "Y_pattern": [162]}, {"X_pattern": [147], "Y_pattern": [162, 227]}, {"X_pattern": [147], "Y_pattern": [162, 178]}, {"X_pattern": [147], "Y_pattern": [162, 178, 227]}, {"X_pattern": [147], "Y_pattern": [178]}, {"X_pattern": [147], "Y_pattern": [178, 227]}, {"X_pattern": [147], "Y_pattern": [56]}, {"X_pattern": [147], "Y_pattern": [56, 162]}, {"X_pattern": [147], "Y_pattern": [56, 227]}, {"X_pattern": [147], "Y_pattern": [56, 178]}, {"X_pattern": [147], "Y_pattern": [56, 162, 227]}, {"X_pattern": [147], "Y_pattern": [56, 162, 178]}, {"X_pattern": [147], "Y_pattern": [56, 178, 227]}, {"X_pattern": [147], "Y_pattern": [56, 162, 178, 227]}, {"X_pattern": [147], "Y_pattern": [227]}, {"X_pattern": [157], "Y_pattern": [12]}, {"X_pattern": [157], "Y_pattern": [12, 113]}, {"X_pattern": [157], "Y_pattern": [12, 62]}, {"X_pattern": [157], "Y_pattern": [12, 62, 113]}, {"X_pattern": [157], "Y_pattern": [62]}, {"X_pattern": [157], "Y_pattern": [62, 113]}, {"X_pattern": [157], "Y_pattern": [113]}, {"X_pattern": [162], "Y_pattern": [178]}, {"X_pattern": [162], "Y_pattern": [178, 227]}, {"X_pattern": [162], "Y_pattern": [56]}, {"X_pattern": [162], "Y_pattern": [56, 227]}, {"X_pattern": [162], "Y_pattern": [56, 178]}, {"X_pattern": [162], "Y_pattern": [56, 178, 227]}, {"X_pattern": [162], "Y_pattern": [227]}, {"X_pattern": [169], "Y_pattern": [248]}, {"X_pattern": [170], "Y_pattern": [259]}, {"X_pattern": [170], "Y_pattern": [37]}, {"X_pattern": [170], "Y_pattern": [37, 259]}, {"X_pattern": [170], "Y_pattern": [37, 238]}, {"X_pattern": [170], "Y_pattern": [37, 187]}, {"X_pattern": [170], "Y_pattern": [37, 238, 259]}, {"X_pattern": [170], "Y_pattern": [37, 187, 259]}, {"X_pattern": [170], "Y_pattern": [37, 187, 238]}, {"X_pattern": [170], "Y_pattern": [37, 187, 238, 259]}, {"X_pattern": [170], "Y_pattern": [187]}, {"X_pattern": [170], "Y_pattern": [187, 259]}, {"X_pattern": [170], "Y_pattern": [187, 238]}, {"X_pattern": [170], "Y_pattern": [187, 238, 259]}, {"X_pattern": [170], "Y_pattern": [238]}, {"X_pattern": [170], "Y_pattern": [238, 259]}, {"X_pattern": [178], "Y_pattern": [227]}, {"X_pattern": [187], "Y_pattern": [259]}, {"X_pattern": [187], "Y_pattern": [37]}, {"X_pattern": [187], "Y_pattern": [37, 259]}, {"X_pattern": [187], "Y_pattern": [37, 238]}, {"X_pattern": [187], "Y_pattern": [37, 238, 259]}, {"X_pattern": [187], "Y_pattern": [238]}, {"X_pattern": [187], "Y_pattern": [238, 259]}, {"X_pattern": [203], "Y_pattern": [266]}, {"X_pattern": [204], "Y_pattern": [222]}, {"X_pattern": [234], "Y_pattern": [298]}, {"X_pattern": [238], "Y_pattern": [259]}, {"X_pattern": [252], "Y_pattern": [204]}, {"X_pattern": [252], "Y_pattern": [204, 222]}, {"X_pattern": [252], "Y_pattern": [222]}, {"X_pattern": [252], "Y_pattern": [100]}, {"X_pattern": [252], "Y_pattern": [100, 204]}, {"X_pattern": [252], "Y_pattern": [100, 222]}, {"X_pattern": [252], "Y_pattern": [100, 204, 222]}, {"X_pattern": [1, 27], "Y_pattern": [29]}, {"X_pattern": [1, 27], "Y_pattern": [29, 180]}, {"X_pattern": [1, 27], "Y_pattern": [180]}, {"X_pattern": [1, 29], "Y_pattern": [180]}, {"X_pattern": [1, 122], "Y_pattern": [29]}, {"X_pattern": [1, 122], "Y_pattern": [29, 180]}, {"X_pattern": [1, 122], "Y_pattern": [180]}, {"X_pattern": [12, 62], "Y_pattern": [113]}, {"X_pattern": [12, 84], "Y_pattern": [62]}, {"X_pattern": [12, 84], "Y_pattern": [62, 113]}, {"X_pattern": [12, 84], "Y_pattern": [113]}, {"X_pattern": [12, 157], "Y_pattern": [62]}, {"X_pattern": [12, 157], "Y_pattern": [62, 113]}, {"X_pattern": [12, 157], "Y_pattern": [113]}, {"X_pattern": [14, 83], "Y_pattern": [169]}, {"X_pattern": [14, 83], "Y_pattern": [169, 248]}, {"X_pattern": [14, 83], "Y_pattern": [106]}, {"X_pattern": [14, 83], "Y_pattern": [106, 169]}, {"X_pattern": [14, 83], "Y_pattern": [106, 248]}, {"X_pattern": [14, 83], "Y_pattern": [106, 169, 248]}, {"X_pattern": [14, 83], "Y_pattern": [248]}, {"X_pattern": [14, 106], "Y_pattern": [169]}, {"X_pattern": [14, 106], "Y_pattern": [169, 248]}, {"X_pattern": [14, 106], "Y_pattern": [248]}, {"X_pattern": [14, 169], "Y_pattern": [248]}, {"X_pattern": [17, 31], "Y_pattern": [298]}, {"X_pattern": [17, 31], "Y_pattern": [234]}, {"X_pattern": [17, 31], "Y_pattern": [234, 298]}, {"X_pattern": [17, 67], "Y_pattern": [31]}, {"X_pattern": [17, 67], "Y_pattern": [31, 234]}, {"X_pattern": [17, 67], "Y_pattern": [31, 298]}, {"X_pattern": [17, 67], "Y_pattern": [31, 234, 298]}, {"X_pattern": [17, 67], "Y_pattern": [298]}, {"X_pattern": [17, 67], "Y_pattern": [234]}, {"X_pattern": [17, 67], "Y_pattern": [234, 298]}, {"X_pattern": [17, 234], "Y_pattern": [298]}, {"X_pattern": [27, 122], "Y_pattern": [1]}, {"X_pattern": [27, 122], "Y_pattern": [1, 29]}, {"X_pattern": [27, 122], "Y_pattern": [1, 180]}, {"X_pattern": [27, 122], "Y_pattern": [1, 29, 180]}, {"X_pattern": [27, 122], "Y_pattern": [29]}, {"X_pattern": [27, 122], "Y_pattern": [29, 180]}, {"X_pattern": [27, 122], "Y_pattern": [180]}, {"X_pattern": [29, 122], "Y_pattern": [180]}, {"X_pattern": [31, 67], "Y_pattern": [298]}, {"X_pattern": [31, 67], "Y_pattern": [234]}, {"X_pattern": [31, 67], "Y_pattern": [234, 298]}, {"X_pattern": [31, 234], "Y_pattern": [298]}, {"X_pattern": [33, 102], "Y_pattern": [266]}, {"X_pattern": [33, 102], "Y_pattern": [203]}, {"X_pattern": [33, 102], "Y_pattern": [203, 266]}, {"X_pattern": [33, 120], "Y_pattern": [266]}, {"X_pattern": [33, 120], "Y_pattern": [203]}, {"X_pattern": [33, 120], "Y_pattern": [203, 266]}, {"X_pattern": [33, 203], "Y_pattern": [266]}, {"X_pattern": [37, 187], "Y_pattern": [259]}, {"X_pattern": [37, 187], "Y_pattern": [238]}, {"X_pattern": [37, 187], "Y_pattern": [238, 259]}, {"X_pattern": [37, 238], "Y_pattern": [259]}, {"X_pattern": [42, 45], "Y_pattern": [155]}, {"X_pattern": [42, 45], "Y_pattern": [126]}, {"X_pattern": [42, 45], "Y_pattern": [126, 155]}, {"X_pattern": [42, 58], "Y_pattern": [155]}, {"X_pattern": [42, 58], "Y_pattern": [126]}, {"X_pattern": [42, 58], "Y_pattern": [126, 155]}, {"X_pattern": [42, 126], "Y_pattern": [155]}, {"X_pattern": [45, 58], "Y_pattern": [155]}, {"X_pattern": [45, 58], "Y_pattern": [42]}, {"X_pattern": [45, 58], "Y_pattern": [42, 155]}, {"X_pattern": [45, 58], "Y_pattern": [42, 126]}, {"X_pattern": [45, 58], "Y_pattern": [42, 126, 155]}, {"X_pattern": [45, 58], "Y_pattern": [126]}, {"X_pattern": [45, 58], "Y_pattern": [126, 155]}, {"X_pattern": [45, 126], "Y_pattern": [155]}, {"X_pattern": [56, 147], "Y_pattern": [178]}, {"X_pattern": [56, 147], "Y_pattern": [178, 227]}, {"X_pattern": [56, 147], "Y_pattern": [227]}, {"X_pattern": [56, 162], "Y_pattern": [178]}, {"X_pattern": [56, 162], "Y_pattern": [178, 227]}, {"X_pattern": [56, 162], "Y_pattern": [227]}, {"X_pattern": [56, 178], "Y_pattern": [227]}, {"X_pattern": [58, 126], "Y_pattern": [155]}, {"X_pattern": [62, 157], "Y_pattern": [113]}, {"X_pattern": [64, 69], "Y_pattern": [296]}, {"X_pattern": [64, 69], "Y_pattern": [76]}, {"X_pattern": [64, 69], "Y_pattern": [76, 296]}, {"X_pattern": [64, 79], "Y_pattern": [296]}, {"X_pattern": [64, 79], "Y_pattern": [69]}, {"X_pattern": [64, 79], "Y_pattern": [69, 76]}, {"X_pattern": [64, 79], "Y_pattern": [69, 296]}, {"X_pattern": [64, 79], "Y_pattern": [69, 76, 296]}, {"X_pattern": [64, 79], "Y_pattern": [76]}, {"X_pattern": [64, 79], "Y_pattern": [76, 296]}, {"X_pattern": [67, 234], "Y_pattern": [298]}, {"X_pattern": [69, 76], "Y_pattern": [296]}, {"X_pattern": [69, 79], "Y_pattern": [296]}, {"X_pattern": [69, 79], "Y_pattern": [76]}, {"X_pattern": [69, 79], "Y_pattern": [76, 296]}, {"X_pattern": [76, 79], "Y_pattern": [296]}, {"X_pattern": [83, 106], "Y_pattern": [169]}, {"X_pattern": [83, 106], "Y_pattern": [169, 248]}, {"X_pattern": [83, 106], "Y_pattern": [248]}, {"X_pattern": [83, 169], "Y_pattern": [248]}, {"X_pattern": [84, 157], "Y_pattern": [12]}, {"X_pattern": [84, 157], "Y_pattern": [12, 113]}, {"X_pattern": [84, 157], "Y_pattern": [12, 62]}, {"X_pattern": [84, 157], "Y_pattern": [12, 62, 113]}, {"X_pattern": [84, 157], "Y_pattern": [62]}, {"X_pattern": [84, 157], "Y_pattern": [62, 113]}, {"X_pattern": [84, 157], "Y_pattern": [113]}, {"X_pattern": [93, 100], "Y_pattern": [204]}, {"X_pattern": [93, 100], "Y_pattern": [204, 222]}, {"X_pattern": [93, 100], "Y_pattern": [222]}, {"X_pattern": [93, 252], "Y_pattern": [204]}, {"X_pattern": [93, 252], "Y_pattern": [204, 222]}, {"X_pattern": [93, 252], "Y_pattern": [222]}, {"X_pattern": [93, 252], "Y_pattern": [100]}, {"X_pattern": [93, 252], "Y_pattern": [100, 204]}, {"X_pattern": [93, 252], "Y_pattern": [100, 222]}, {"X_pattern": [93, 252], "Y_pattern": [100, 204, 222]}, {"X_pattern": [100, 204], "Y_pattern": [222]}, {"X_pattern": [100, 252], "Y_pattern": [204]}, {"X_pattern": [100, 252], "Y_pattern": [204, 222]}, {"X_pattern": [100, 252], "Y_pattern": [222]}, {"X_pattern": [102, 120], "Y_pattern": [266]}, {"X_pattern": [102, 120], "Y_pattern": [33]}, {"X_pattern": [102, 120], "Y_pattern": [33, 266]}, {"X_pattern": [102, 120], "Y_pattern": [33, 203]}, {"X_pattern": [102, 120], "Y_pattern": [33, 203, 266]}, {"X_pattern": [102, 120], "Y_pattern": [203]}, {"X_pattern": [102, 120], "Y_pattern": [203, 266]}, {"X_pattern": [102, 203], "Y_pattern": [266]}, {"X_pattern": [106, 169], "Y_pattern": [248]}, {"X_pattern": [120, 203], "Y_pattern": [266]}, {"X_pattern": [147, 162], "Y_pattern": [178]}, {"X_pattern": [147, 162], "Y_pattern": [178, 227]}, {"X_pattern": [147, 162], "Y_pattern": [56]}, {"X_pattern": [147, 162], "Y_pattern": [56, 227]}, {"X_pattern": [147, 162], "Y_pattern": [56, 178]}, {"X_pattern": [147, 162], "Y_pattern": [56, 178, 227]}, {"X_pattern": [147, 162], "Y_pattern": [227]}, {"X_pattern": [147, 178], "Y_pattern": [227]}, {"X_pattern": [162, 178], "Y_pattern": [227]}, {"X_pattern": [170, 187], "Y_pattern": [259]}, {"X_pattern": [170, 187], "Y_pattern": [37]}, {"X_pattern": [170, 187], "Y_pattern": [37, 259]}, {"X_pattern": [170, 187], "Y_pattern": [37, 238]}, {"X_pattern": [170, 187], "Y_pattern": [37, 238, 259]}, {"X_pattern": [170, 187], "Y_pattern": [238]}, {"X_pattern": [170, 187], "Y_pattern": [238, 259]}, {"X_pattern": [187, 238], "Y_pattern": [259]}, {"X_pattern": [204, 252], "Y_pattern": [222]}, {"X_pattern": [1, 27, 29], "Y_pattern": [180]}, {"X_pattern": [1, 27, 122], "Y_pattern": [29]}, {"X_pattern": [1, 27, 122], "Y_pattern": [29, 180]}, {"X_pattern": [1, 27, 122], "Y_pattern": [180]}, {"X_pattern": [1, 29, 122], "Y_pattern": [180]}, {"X_pattern": [12, 62, 157], "Y_pattern": [113]}, {"X_pattern": [12, 84, 157], "Y_pattern": [62]}, {"X_pattern": [12, 84, 157], "Y_pattern": [62, 113]}, {"X_pattern": [12, 84, 157], "Y_pattern": [113]}, {"X_pattern": [14, 83, 106], "Y_pattern": [169]}, {"X_pattern": [14, 83, 106], "Y_pattern": [169, 248]}, {"X_pattern": [14, 83, 106], "Y_pattern": [248]}, {"X_pattern": [14, 83, 169], "Y_pattern": [248]}, {"X_pattern": [14, 106, 169], "Y_pattern": [248]}, {"X_pattern": [17, 31, 67], "Y_pattern": [298]}, {"X_pattern": [17, 31, 67], "Y_pattern": [234]}, {"X_pattern": [17, 31, 67], "Y_pattern": [234, 298]}, {"X_pattern": [17, 31, 234], "Y_pattern": [298]}, {"X_pattern": [17, 67, 234], "Y_pattern": [298]}, {"X_pattern": [27, 29, 122], "Y_pattern": [180]}, {"X_pattern": [31, 67, 234], "Y_pattern": [298]}, {"X_pattern": [33, 102, 120], "Y_pattern": [266]}, {"X_pattern": [33, 102, 120], "Y_pattern": [203]}, {"X_pattern": [33, 102, 120], "Y_pattern": [203, 266]}, {"X_pattern": [33, 102, 203], "Y_pattern": [266]}, {"X_pattern": [33, 120, 203], "Y_pattern": [266]}, {"X_pattern": [37, 170, 187], "Y_pattern": [259]}, {"X_pattern": [37, 170, 187], "Y_pattern": [238]}, {"X_pattern": [37, 170, 187], "Y_pattern": [238, 259]}, {"X_pattern": [37, 187, 238], "Y_pattern": [259]}, {"X_pattern": [42, 45, 58], "Y_pattern": [155]}, {"X_pattern": [42, 45, 58], "Y_pattern": [126]}, {"X_pattern": [42, 45, 58], "Y_pattern": [126, 155]}, {"X_pattern": [42, 45, 126], "Y_pattern": [155]}, {"X_pattern": [42, 58, 126], "Y_pattern": [155]}, {"X_pattern": [45, 58, 126], "Y_pattern": [155]}, {"X_pattern": [56, 147, 162], "Y_pattern": [178]}, {"X_pattern": [56, 147, 162], "Y_pattern": [178, 227]}, {"X_pattern": [56, 147, 162], "Y_pattern": [227]}, {"X_pattern": [56, 147, 178], "Y_pattern": [227]}, {"X_pattern": [56, 162, 178], "Y_pattern": [227]}, {"X_pattern": [64, 69, 79], "Y_pattern": [296]}, {"X_pattern": [64, 69, 79], "Y_pattern": [76]}, {"X_pattern": [64, 69, 79], "Y_pattern": [76, 296]}, {"X_pattern": [64, 76, 79], "Y_pattern": [296]}, {"X_pattern": [69, 76, 79], "Y_pattern": [296]}, {"X_pattern": [83, 106, 169], "Y_pattern": [248]}, {"X_pattern": [93, 100, 252], "Y_pattern": [204]}, {"X_pattern": [93, 100, 252], "Y_pattern": [204, 222]}, {"X_pattern": [93, 100, 252], "Y_pattern": [222]}, {"X_pattern": [93, 204, 252], "Y_pattern": [222]}, {"X_pattern": [100, 204, 252], "Y_pattern": [222]}, {"X_pattern": [102, 120, 203], "Y_pattern": [266]}, {"X_pattern": [147, 162, 178], "Y_pattern": [227]}, {"X_pattern": [1, 27, 29, 122], "Y_pattern": [180]}, {"X_pattern": [14, 83, 106, 169], "Y_pattern": [248]}, {"X_pattern": [17, 31, 67, 234], "Y_pattern": [298]}, {"X_pattern": [33, 102, 120, 203], "Y_pattern": [266]}, {"X_pattern": [42, 45, 58, 126], "Y_pattern": [155]}, {"X_pattern": [56, 147, 162, 178], "Y_pattern": [227]}, {"X_pattern": [64, 69, 76, 79], "Y_pattern": [296]}, {"X_pattern": [93, 100, 204, 252], "Y_pattern": [222]}], "precision": 0.039978902953586505, "recall": 0.8333333333333333, "F1": 0.07629745943551959}