{"model": [{"X_pattern": [74], "Y_pattern": [479], "supp": 14, "conf": 0.6666666666666666}, {"X_pattern": [476], "Y_pattern": [146], "supp": 8, "conf": 0.8}, {"X_pattern": [234], "Y_pattern": [360], "supp": 10, "conf": 0.8333333333333334}, {"X_pattern": [461], "Y_pattern": [47], "supp": 12, "conf": 0.8}, {"X_pattern": [156], "Y_pattern": [73], "supp": 5, "conf": 0.7142857142857143}, {"X_pattern": [9], "Y_pattern": [166], "supp": 7, "conf": 0.7}, {"X_pattern": [444], "Y_pattern": [415], "supp": 6, "conf": 0.6666666666666666}, {"X_pattern": [341], "Y_pattern": [52], "supp": 6, "conf": 0.6666666666666666}, {"X_pattern": [202], "Y_pattern": [2], "supp": 12, "conf": 0.7058823529411765}, {"X_pattern": [46], "Y_pattern": [284], "supp": 6, "conf": 0.8571428571428571}, {"X_pattern": [471], "Y_pattern": [412], "supp": 6, "conf": 0.6}, {"X_pattern": [210], "Y_pattern": [49], "supp": 7, "conf": 0.7}, {"X_pattern": [495], "Y_pattern": [336], "supp": 8, "conf": 0.8888888888888888}, {"X_pattern": [270], "Y_pattern": [129], "supp": 7, "conf": 0.7}, {"X_pattern": [492], "Y_pattern": [199], "supp": 8, "conf": 1.0}, {"X_pattern": [423], "Y_pattern": [243], "supp": 4, "conf": 0.8}, {"X_pattern": [81], "Y_pattern": [26], "supp": 5, "conf": 0.8333333333333334}, {"X_pattern": [80], "Y_pattern": [282], "supp": 5, "conf": 0.45454545454545453}, {"X_pattern": [152], "Y_pattern": [316], "supp": 6, "conf": 0.6}, {"X_pattern": [232], "Y_pattern": [99], "supp": 7, "conf": 0.7}], "total_encoding_cost": 52760.38405038524, "miner_runtime": 1.9354799707730612, "hypercompressed_model": [{"X_pattern": [74], "Y_pattern": [479], "supp": 14, "conf": 0.6666666666666666}, {"X_pattern": [476], "Y_pattern": [146], "supp": 8, "conf": 0.8}, {"X_pattern": [234], "Y_pattern": [360], "supp": 10, "conf": 0.8333333333333334}, {"X_pattern": [461], "Y_pattern": [47], "supp": 12, "conf": 0.8}, {"X_pattern": [156], "Y_pattern": [73], "supp": 5, "conf": 0.7142857142857143}, {"X_pattern": [9], "Y_pattern": [166], "supp": 7, "conf": 0.7}, {"X_pattern": [444], "Y_pattern": [415], "supp": 6, "conf": 0.6666666666666666}, {"X_pattern": [341], "Y_pattern": [52], "supp": 6, "conf": 0.6666666666666666}, {"X_pattern": [202], "Y_pattern": [2], "supp": 12, "conf": 0.7058823529411765}, {"X_pattern": [46], "Y_pattern": [284], "supp": 6, "conf": 0.8571428571428571}, {"X_pattern": [471], "Y_pattern": [412], "supp": 6, "conf": 0.6}, {"X_pattern": [210], "Y_pattern": [49], "supp": 7, "conf": 0.7}, {"X_pattern": [495], "Y_pattern": [336], "supp": 8, "conf": 0.8888888888888888}, {"X_pattern": [270], "Y_pattern": [129], "supp": 7, "conf": 0.7}, {"X_pattern": [492], "Y_pattern": [199], "supp": 8, "conf": 1.0}, {"X_pattern": [423], "Y_pattern": [243], "supp": 4, "conf": 0.8}, {"X_pattern": [81], "Y_pattern": [26], "supp": 5, "conf": 0.8333333333333334}, {"X_pattern": [80], "Y_pattern": [282], "supp": 5, "conf": 0.45454545454545453}, {"X_pattern": [152], "Y_pattern": [316], "supp": 6, "conf": 0.6}, {"X_pattern": [232], "Y_pattern": [99], "supp": 7, "conf": 0.7}], "precision": 1.0, "recall": 1.0, "F1": 1.0}